<?xml version="1.0" encoding="UTF-8"?>
<tv generator-info-name="WebGrab+Plus/w MDB &amp; REX Postprocess -- version  V3.2.0.0 -- Jan van Straaten" generator-info-url="http://www.webgrabplus.com">
  <channel id="Canal Uno (Ecuador)">
    <display-name lang="es">Canal Uno (Ecuador)</display-name>
    <url>http://www.gatotv.com</url>
  </channel>
  <channel id="Canal Ecuavisa (Ecuador)">
    <display-name lang="es">Canal Ecuavisa (Ecuador)</display-name>
    <url>http://www.gatotv.com</url>
  </channel>
  <channel id="Canal Teleamazonas ">
    <display-name lang="es">Canal Teleamazonas </display-name>
    <url>http://www.gatotv.com</url>
  </channel>
  <channel id="Canal TC Televisión">
    <display-name lang="es">Canal TC Televisión</display-name>
    <url>http://www.gatotv.com</url>
  </channel>
  <channel id="Canal Gamavisión">
    <display-name lang="es">Canal Gamavisión</display-name>
    <url>http://www.gatotv.com</url>
  </channel>
  <channel id="Canal RTS">
    <display-name lang="es">Canal RTS</display-name>
    <url>http://www.gatotv.com</url>
  </channel>
  <channel id="Canal GolTV Latinoamérica">
    <display-name lang="es">Canal GolTV Latinoamérica</display-name>
    <url>http://www.gatotv.com</url>
  </channel>
  <channel id="Canal Cinemax (México)">
    <display-name lang="es">Canal Cinemax (México)</display-name>
    <url>http://www.gatotv.com</url>
  </channel>
  <channel id="Canal National Geographic (Centro)">
    <display-name lang="es">Canal National Geographic (Centro)</display-name>
    <url>http://www.gatotv.com</url>
  </channel>
  <channel id="Canal ESPN 2 (Colombia)">
    <display-name lang="es">Canal ESPN 2 (Colombia)</display-name>
    <url>http://www.gatotv.com</url>
  </channel>
  <channel id="Canal Warner TV (Panregional)">
    <display-name lang="es">Canal Warner TV (Panregional)</display-name>
    <url>http://www.gatotv.com</url>
  </channel>
  <channel id="EC DIRECTV Sports Ecuador">
    <display-name lang="en">EC DIRECTV Sports Ecuador</display-name>
    <url>http://www.directvsports.com</url>
  </channel>
  <channel id="EC DIRECTV Sports 2">
    <display-name lang="en">EC DIRECTV Sports 2</display-name>
    <url>http://www.directvsports.com</url>
  </channel>
  <channel id="EC DIRECTV Sports Plus">
    <display-name lang="en">EC DIRECTV Sports Plus</display-name>
    <url>http://www.directvsports.com</url>
  </channel>
  <channel id="Win Sports +">
    <display-name lang="en">Win Sports +</display-name>
    <url>http://www.winsportsonline.com</url>
  </channel>
  <channel id="Showtime Familyzone West">
    <display-name lang="en">Showtime Familyzone West</display-name>
    <icon src="https://m.media-amazon.com/images/G/01/digital/video/merch/subs/benefit-id/s-z/showtimeSub/live/showtime_Family_blck._CB1557794632_.svg" />
    <url>http://www.amazon.com</url>
  </channel>
  <channel id="Starz HD East (Dolby Available)">
    <display-name lang="en">Starz HD East (Dolby Available)</display-name>
    <icon src="https://m.media-amazon.com/images/G/01/digital/video/merch/subs/benefit-id/s-z/starzSub/live/Starz_HD_East_black._CB1557794728_.svg" />
    <url>http://www.amazon.com</url>
  </channel>
  <channel id="Starz Edge HD East">
    <display-name lang="en">Starz Edge HD East</display-name>
    <icon src="https://m.media-amazon.com/images/G/01/digital/video/merch/subs/benefit-id/s-z/starzSub/live/Starz_EDGE_HD_East_blck._CB1557794728_.svg" />
    <url>http://www.amazon.com</url>
  </channel>
  <channel id="Starz Kids &amp; Family HD East">
    <display-name lang="en">Starz Kids &amp; Family HD East</display-name>
    <icon src="https://m.media-amazon.com/images/G/01/digital/video/merch/subs/benefit-id/s-z/starzSub/live/Starz_KIDS_FAMILY_HD_East_blck._CB1557794729_.svg" />
    <url>http://www.amazon.com</url>
  </channel>
  <channel id="Starz inBlack HD East">
    <display-name lang="en">Starz inBlack HD East</display-name>
    <icon src="https://m.media-amazon.com/images/G/01/digital/video/merch/subs/benefit-id/s-z/starzSub/live/Starz_INBLACK_HD_East_blck._CB1557794729_.svg" />
    <url>http://www.amazon.com</url>
  </channel>
  <channel id="Starz Cinema HD East">
    <display-name lang="en">Starz Cinema HD East</display-name>
    <icon src="https://m.media-amazon.com/images/G/01/digital/video/merch/subs/benefit-id/s-z/starzSub/live/Starz_CINEMA_HD_East_blck._CB1557794727_.svg" />
    <url>http://www.amazon.com</url>
  </channel>
  <channel id="Starz Comedy HD East">
    <display-name lang="en">Starz Comedy HD East</display-name>
    <icon src="https://m.media-amazon.com/images/G/01/digital/video/merch/subs/benefit-id/s-z/starzSub/live/Starz_COMEDY_HD_East_blck._CB1557794728_.svg" />
    <url>http://www.amazon.com</url>
  </channel>
  <channel id="Encore HD East">
    <display-name lang="en">Encore HD East</display-name>
    <icon src="https://m.media-amazon.com/images/G/01/digital/video/merch/subs/benefit-id/s-z/starzSub/live/Starz_ENCORE_HD_East_blck._CB1557794728_.svg" />
    <url>http://www.amazon.com</url>
  </channel>
  <channel id="Encore Action HD East">
    <display-name lang="en">Encore Action HD East</display-name>
    <icon src="https://m.media-amazon.com/images/G/01/digital/video/merch/subs/benefit-id/s-z/starzSub/live/Starz_ENCORE_ACTION_East_blck._CB1557794728_.svg" />
    <url>http://www.amazon.com</url>
  </channel>
  <channel id="L'EQUIPE">
    <display-name lang="fr">L'EQUIPE</display-name>
    <url>http://www.canalplus.com</url>
  </channel>
  <channel id="GOLPERU HD (GOLPERU HD)">
    <display-name lang="es">GOLPERU HD (GOLPERU HD)</display-name>
    <icon src="http://media.gvp.telefonica.com/storagearea0/IMAGES/00/07/55/7553956_D7D9A30FB187AF45.png" />
    <url>http://www.movistar.com.pe</url>
  </channel>
  <programme start="20220330013000 -0600" stop="20220330023000 -0600" channel="Canal Ecuavisa (Ecuador)">
    <title lang="es">Tres familias</title>
  </programme>
  <programme start="20220330023000 -0600" stop="20220330050000 -0600" channel="Canal Ecuavisa (Ecuador)">
    <title lang="es">El Combo Amarillo</title>
  </programme>
  <programme start="20220330050000 -0600" stop="20220330055500 -0600" channel="Canal Ecuavisa (Ecuador)">
    <title lang="es">Telenovela</title>
  </programme>
  <programme start="20220330055500 -0600" stop="20220330065500 -0600" channel="Canal Ecuavisa (Ecuador)">
    <title lang="es">Televistazo</title>
  </programme>
  <programme start="20220330065500 -0600" stop="20220330073000 -0600" channel="Canal Ecuavisa (Ecuador)">
    <title lang="es">Contacto directo</title>
  </programme>
  <programme start="20220330073000 -0600" stop="20220330090000 -0600" channel="Canal Ecuavisa (Ecuador)">
    <title lang="es">Televistazo</title>
  </programme>
  <programme start="20220330090000 -0600" stop="20220330103000 -0600" channel="Canal Ecuavisa (Ecuador)">
    <title lang="es">Hermanas</title>
  </programme>
  <programme start="20220330103000 -0600" stop="20220330130000 -0600" channel="Canal Ecuavisa (Ecuador)">
    <title lang="es">En Contacto</title>
  </programme>
  <programme start="20220330130000 -0600" stop="20220330140000 -0600" channel="Canal Ecuavisa (Ecuador)">
    <title lang="es">Televistazo</title>
  </programme>
  <programme start="20220330140000 -0600" stop="20220330150000 -0600" channel="Canal Ecuavisa (Ecuador)">
    <title lang="es">Perro amor</title>
  </programme>
  <programme start="20220330150000 -0600" stop="20220330160000 -0600" channel="Canal Ecuavisa (Ecuador)">
    <title lang="es">Beyhadh</title>
  </programme>
  <programme start="20220330160000 -0600" stop="20220330170000 -0600" channel="Canal Ecuavisa (Ecuador)">
    <title lang="es">Amor Sincero</title>
  </programme>
  <programme start="20220330170000 -0600" stop="20220330180000 -0600" channel="Canal Ecuavisa (Ecuador)">
    <title lang="es">Pura Sangre</title>
  </programme>
  <programme start="20220330180000 -0600" stop="20220330190000 -0600" channel="Canal Ecuavisa (Ecuador)">
    <title lang="es">La heredera</title>
  </programme>
  <programme start="20220330190000 -0600" stop="20220330200000 -0600" channel="Canal Ecuavisa (Ecuador)">
    <title lang="es">Televistazo</title>
  </programme>
  <programme start="20220330200000 -0600" stop="20220330210000 -0600" channel="Canal Ecuavisa (Ecuador)">
    <title lang="es">Amor eterno</title>
  </programme>
  <programme start="20220330210000 -0600" stop="20220330220000 -0600" channel="Canal Ecuavisa (Ecuador)">
    <title lang="es">No llores por mí</title>
  </programme>
  <programme start="20220330220000 -0600" stop="20220330230000 -0600" channel="Canal Ecuavisa (Ecuador)">
    <title lang="es">Huérfanos de su tierra</title>
  </programme>
  <programme start="20220330230000 -0600" stop="20220331000000 -0600" channel="Canal Ecuavisa (Ecuador)">
    <title lang="es">Tres familias</title>
  </programme>
  <programme start="20220330001500 -0600" stop="20220330011500 -0600" channel="Canal Teleamazonas ">
    <title lang="es">Homeland</title>
    <title lang="xx">Homeland</title>
    <desc lang="es">Una oficial de la CIA se convence a si misma que el rescate de un soldado dado por muerto años atrás se trata de un complot de Al Qaeda en suelo americano.(n)</desc>
    <credits>
      <actor>Claire Danes</actor>
      <actor>Damian Lewis</actor>
      <actor>Morena Baccarin</actor>
      <actor>David Harewood</actor>
      <actor>Diego Klattenhoff</actor>
      <actor>Jackson Pace</actor>
      <actor>Morgan Saylor</actor>
      <actor>Mandy Patinkin</actor>
      <producer>Lauren White</producer>
      <producer>Katie O'Hara</producer>
      <composer>Sean Callery</composer>
    </credits>
    <date>2011</date>
    <category lang="es">Serie</category>
    <icon src="https://imagenes.gatotv.com/categorias/programas/miniatura/homeland.jpg" />
    <rating>
      <value>TV-MA</value>
    </rating>
  </programme>
  <programme start="20220330011500 -0600" stop="20220330020000 -0600" channel="Canal Teleamazonas ">
    <title lang="es">Vivos</title>
  </programme>
  <programme start="20220330020000 -0600" stop="20220330023000 -0600" channel="Canal Teleamazonas ">
    <title lang="es">Programación no disponible</title>
  </programme>
  <programme start="20220330023000 -0600" stop="20220330024500 -0600" channel="Canal Teleamazonas ">
    <title lang="es">24 horas</title>
  </programme>
  <programme start="20220330024500 -0600" stop="20220330033000 -0600" channel="Canal Teleamazonas ">
    <title lang="es">Divino niño</title>
  </programme>
  <programme start="20220330033000 -0600" stop="20220330040000 -0600" channel="Canal Teleamazonas ">
    <title lang="es">Educa</title>
  </programme>
  <programme start="20220330040000 -0600" stop="20220330050000 -0600" channel="Canal Teleamazonas ">
    <title lang="es">El Doctor milagro</title>
  </programme>
  <programme start="20220330050000 -0600" stop="20220330055500 -0600" channel="Canal Teleamazonas ">
    <title lang="es">Pedro el Escamoso</title>
  </programme>
  <programme start="20220330055500 -0600" stop="20220330070000 -0600" channel="Canal Teleamazonas ">
    <title lang="es">24 Horas</title>
  </programme>
  <programme start="20220330070000 -0600" stop="20220330073000 -0600" channel="Canal Teleamazonas ">
    <title lang="es">24 horas nacional</title>
  </programme>
  <programme start="20220330073000 -0600" stop="20220330080000 -0600" channel="Canal Teleamazonas ">
    <title lang="es">Entrevistas en 24 horas</title>
  </programme>
  <programme start="20220330080000 -0600" stop="20220330093000 -0600" channel="Canal Teleamazonas ">
    <title lang="es">24 Horas</title>
  </programme>
  <programme start="20220330093000 -0600" stop="20220330113000 -0600" channel="Canal Teleamazonas ">
    <title lang="es">Madre</title>
  </programme>
  <programme start="20220330113000 -0600" stop="20220330123000 -0600" channel="Canal Teleamazonas ">
    <title lang="es">Boys Over Flowers</title>
  </programme>
  <programme start="20220330123000 -0600" stop="20220330130000 -0600" channel="Canal Teleamazonas ">
    <title lang="es">Programación no disponible</title>
  </programme>
  <programme start="20220330130000 -0600" stop="20220330135500 -0600" channel="Canal Teleamazonas ">
    <title lang="es">24 Horas</title>
  </programme>
  <programme start="20220330135500 -0600" stop="20220330143000 -0600" channel="Canal Teleamazonas ">
    <title lang="es">Comunidad</title>
  </programme>
  <programme start="20220330143000 -0600" stop="20220330144200 -0600" channel="Canal Teleamazonas ">
    <title lang="es">En Corto</title>
  </programme>
  <programme start="20220330144200 -0600" stop="20220330150000 -0600" channel="Canal Teleamazonas ">
    <title lang="es">Deporte Total</title>
  </programme>
  <programme start="20220330150000 -0600" stop="20220330160000 -0600" channel="Canal Teleamazonas ">
    <title lang="es">Bob Esponja</title>
  </programme>
  <programme start="20220330160000 -0600" stop="20220330163000 -0600" channel="Canal Teleamazonas ">
    <title lang="es">Los Pingüinos de Madagascar</title>
    <title lang="xx">The Penguins of Madagascar</title>
    <desc lang="es">Cuatro pingüinos que viven en el zoológico de Central Park en Nueva York deben usar sus habilidades de comando de primer nivel para resolver misiones.(n)</desc>
    <date>2008</date>
    <category lang="es">Animación</category>
    <icon src="https://imagenes.gatotv.com/categorias/caricaturas/miniatura/los_pinguinos_de_madagascar.jpg" />
    <rating>
      <value>TV-PG</value>
    </rating>
  </programme>
  <programme start="20220330163000 -0600" stop="20220330170000 -0600" channel="Canal Teleamazonas ">
    <title lang="es">Doraemon</title>
  </programme>
  <programme start="20220330170000 -0600" stop="20220330180000 -0600" channel="Canal Teleamazonas ">
    <title lang="es">Futurama</title>
  </programme>
  <programme start="20220330180000 -0600" stop="20220330190000 -0600" channel="Canal Teleamazonas ">
    <title lang="es">Nuevo rico, nuevo pobre</title>
  </programme>
  <programme start="20220330190000 -0600" stop="20220330200000 -0600" channel="Canal Teleamazonas ">
    <title lang="es">Los Simpson</title>
    <desc lang="es">Una parodia satírica que cuenta las aventuras de los famosos personajes Homero, Marge, Bart, Lisa y Maggie de Springfield.(n)</desc>
    <date>1989</date>
    <category lang="es">Caricatura</category>
    <category lang="es">Programa</category>
    <category lang="es">Serie</category>
    <icon src="https://imagenes.gatotv.com/categorias/programas/miniatura/los_simpson.png" />
  </programme>
  <programme start="20220330200000 -0600" stop="20220330210000 -0600" channel="Canal Teleamazonas ">
    <title lang="es">24 Horas</title>
  </programme>
  <programme start="20220330210000 -0600" stop="20220330220000 -0600" channel="Canal Teleamazonas ">
    <title lang="es">La nieta elegida</title>
  </programme>
  <programme start="20220330220000 -0600" stop="20220330230000 -0600" channel="Canal Teleamazonas ">
    <title lang="es">Almas Heridas</title>
  </programme>
  <programme start="20220330230000 -0600" stop="20220330231000 -0600" channel="Canal Teleamazonas ">
    <title lang="es">La ley secreta</title>
  </programme>
  <programme start="20220330010000 -0600" stop="20220330020000 -0600" channel="Canal TC Televisión">
    <title lang="es">Prueba de Fe</title>
  </programme>
  <programme start="20220330020000 -0600" stop="20220330023000 -0600" channel="Canal TC Televisión">
    <title lang="es">Prueba de Fe</title>
  </programme>
  <programme start="20220330023000 -0600" stop="20220330040000 -0600" channel="Canal TC Televisión">
    <title lang="es">De boca en boca - DBEB</title>
  </programme>
  <programme start="20220330040000 -0600" stop="20220330050000 -0600" channel="Canal TC Televisión">
    <title lang="es">EDUCA</title>
  </programme>
  <programme start="20220330050000 -0600" stop="20220330051500 -0600" channel="Canal TC Televisión">
    <title lang="es">José de los Santos</title>
  </programme>
  <programme start="20220330051500 -0600" stop="20220330054500 -0600" channel="Canal TC Televisión">
    <title lang="es">Alerta Roja</title>
  </programme>
  <programme start="20220330054500 -0600" stop="20220330070000 -0600" channel="Canal TC Televisión">
    <title lang="es">DespiérTC</title>
  </programme>
  <programme start="20220330070000 -0600" stop="20220330083000 -0600" channel="Canal TC Televisión">
    <title lang="es">El noticiero I</title>
  </programme>
  <programme start="20220330083000 -0600" stop="20220330100000 -0600" channel="Canal TC Televisión">
    <title lang="es">Entre ellas</title>
  </programme>
  <programme start="20220330100000 -0600" stop="20220330113000 -0600" channel="Canal TC Televisión">
    <title lang="es">De Casa en Casa</title>
  </programme>
  <programme start="20220330113000 -0600" stop="20220330123000 -0600" channel="Canal TC Televisión">
    <title lang="es">Rostro de justicia</title>
  </programme>
  <programme start="20220330123000 -0600" stop="20220330140000 -0600" channel="Canal TC Televisión">
    <title lang="es">El noticiero II</title>
  </programme>
  <programme start="20220330140000 -0600" stop="20220330150000 -0600" channel="Canal TC Televisión">
    <title lang="es">Rendón y La Bombón</title>
  </programme>
  <programme start="20220330150000 -0600" stop="20220330160000 -0600" channel="Canal TC Televisión">
    <title lang="es">Casi cuarentonas</title>
  </programme>
  <programme start="20220330160000 -0600" stop="20220330173000 -0600" channel="Canal TC Televisión">
    <title lang="es">De boca en boca</title>
  </programme>
  <programme start="20220330173000 -0600" stop="20220330190000 -0600" channel="Canal TC Televisión">
    <title lang="es">Soy el mejor</title>
  </programme>
  <programme start="20220330190000 -0600" stop="20220330203000 -0600" channel="Canal TC Televisión">
    <title lang="es">El Noticiero III</title>
  </programme>
  <programme start="20220330203000 -0600" stop="20220330210000 -0600" channel="Canal TC Televisión">
    <title lang="es">Luz de luna</title>
  </programme>
  <programme start="20220330210000 -0600" stop="20220330214500 -0600" channel="Canal TC Televisión">
    <title lang="es">La inocencia de Tania</title>
  </programme>
  <programme start="20220330214500 -0600" stop="20220330223000 -0600" channel="Canal TC Televisión">
    <title lang="es">Amor de familia</title>
  </programme>
  <programme start="20220330223000 -0600" stop="20220330233000 -0600" channel="Canal TC Televisión">
    <title lang="es">Vera... a su manera</title>
  </programme>
  <programme start="20220330233000 -0600" stop="20220331000000 -0600" channel="Canal TC Televisión">
    <title lang="es">Alerta Roja</title>
  </programme>
  <programme start="20220330060000 -0600" stop="20220330070000 -0600" channel="Canal Gamavisión">
    <title lang="es">Gamanoticias matinal</title>
  </programme>
  <programme start="20220330070000 -0600" stop="20220330073000 -0600" channel="Canal Gamavisión">
    <title lang="es">Pensadores positivos</title>
  </programme>
  <programme start="20220330073000 -0600" stop="20220330090000 -0600" channel="Canal Gamavisión">
    <title lang="es">Outlet TV</title>
  </programme>
  <programme start="20220330090000 -0600" stop="20220330093000 -0600" channel="Canal Gamavisión">
    <title lang="es">LABMAC</title>
  </programme>
  <programme start="20220330093000 -0600" stop="20220330100000 -0600" channel="Canal Gamavisión">
    <title lang="es">Outlet TV</title>
  </programme>
  <programme start="20220330100000 -0600" stop="20220330110000 -0600" channel="Canal Gamavisión">
    <title lang="es">Outlet TV</title>
  </programme>
  <programme start="20220330110000 -0600" stop="20220330113000 -0600" channel="Canal Gamavisión">
    <title lang="es">Candy Candy</title>
  </programme>
  <programme start="20220330113000 -0600" stop="20220330123000 -0600" channel="Canal Gamavisión">
    <title lang="es">El bigote del sabor</title>
  </programme>
  <programme start="20220330123000 -0600" stop="20220330140000 -0600" channel="Canal Gamavisión">
    <title lang="es">Quienes mandan aquí</title>
  </programme>
  <programme start="20220330140000 -0600" stop="20220330143000 -0600" channel="Canal Gamavisión">
    <title lang="es">Numerología</title>
  </programme>
  <programme start="20220330143000 -0600" stop="20220330153000 -0600" channel="Canal Gamavisión">
    <title lang="es">Programa deportivo</title>
  </programme>
  <programme start="20220330153000 -0600" stop="20220330160000 -0600" channel="Canal Gamavisión">
    <title lang="es">Animado</title>
  </programme>
  <programme start="20220330160000 -0600" stop="20220330170000 -0600" channel="Canal Gamavisión">
    <title lang="es">Tik Music</title>
  </programme>
  <programme start="20220330170000 -0600" stop="20220330173000 -0600" channel="Canal Gamavisión">
    <title lang="es">Dueña y Señora</title>
  </programme>
  <programme start="20220330173000 -0600" stop="20220330180000 -0600" channel="Canal Gamavisión">
    <title lang="es">Tabú</title>
  </programme>
  <programme start="20220330180000 -0600" stop="20220330190000 -0600" channel="Canal Gamavisión">
    <title lang="es">El bigote del sabor</title>
  </programme>
  <programme start="20220330190000 -0600" stop="20220330200000 -0600" channel="Canal Gamavisión">
    <title lang="es">Gamanoticias estelar</title>
  </programme>
  <programme start="20220330200000 -0600" stop="20220330210000 -0600" channel="Canal Gamavisión">
    <title lang="es">Secretarias</title>
  </programme>
  <programme start="20220330210000 -0600" stop="20220330230000 -0600" channel="Canal Gamavisión">
    <title lang="es">Quienes mandan aquí</title>
  </programme>
  <programme start="20220330230000 -0600" stop="20220330233000 -0600" channel="Canal Gamavisión">
    <title lang="es">LABMAC</title>
  </programme>
  <programme start="20220330233000 -0600" stop="20220331000000 -0600" channel="Canal Gamavisión">
    <title lang="es">Archivos del destino</title>
  </programme>
  <programme start="20220330001500 -0600" stop="20220330010000 -0600" channel="Canal RTS">
    <title lang="es">The Walking Dead</title>
    <desc lang="es">Serie que presenta la aclamada serie de historietas de Robert Kirkman con el mismo nombre donde un Sheriff se ve en un mundo lleno de Zombies.(n)</desc>
    <credits>
      <actor>Andrew Lincoln</actor>
      <actor>Jon Bernthal</actor>
      <actor>Sarah Wayne Callies</actor>
      <composer>Bear McCreary</composer>
    </credits>
    <date>2010</date>
    <category lang="es">Serie</category>
    <category lang="es">Programa</category>
    <icon src="https://imagenes.gatotv.com/categorias/programas/miniatura/the_walking_dead.png" />
  </programme>
  <programme start="20220330010000 -0600" stop="20220330040000 -0600" channel="Canal RTS">
    <title lang="es">Novedades TV</title>
  </programme>
  <programme start="20220330040000 -0600" stop="20220330050000 -0600" channel="Canal RTS">
    <title lang="es">Educa televisión para aprender</title>
  </programme>
  <programme start="20220330050000 -0600" stop="20220330060000 -0600" channel="Canal RTS">
    <title lang="es">La noticia</title>
  </programme>
  <programme start="20220330060000 -0600" stop="20220330070000 -0600" channel="Canal RTS">
    <title lang="es">El despertar de La Noticia</title>
  </programme>
  <programme start="20220330070000 -0600" stop="20220330080000 -0600" channel="Canal RTS">
    <title lang="es">La noticia</title>
  </programme>
  <programme start="20220330080000 -0600" stop="20220330093000 -0600" channel="Canal RTS">
    <title lang="es">La noticia en la comunidad</title>
  </programme>
  <programme start="20220330093000 -0600" stop="20220330110000 -0600" channel="Canal RTS">
    <title lang="es">Noticias de la mañana</title>
  </programme>
  <programme start="20220330110000 -0600" stop="20220330120000 -0600" channel="Canal RTS">
    <title lang="es">Mujer, casos de la vida real</title>
  </programme>
  <programme start="20220330120000 -0600" stop="20220330130000 -0600" channel="Canal RTS">
    <title lang="es">La Familia de Mi Esposo</title>
  </programme>
  <programme start="20220330130000 -0600" stop="20220330140000 -0600" channel="Canal RTS">
    <title lang="es">La Rosa de Guadalupe</title>
  </programme>
  <programme start="20220330140000 -0600" stop="20220330150000 -0600" channel="Canal RTS">
    <title lang="es">Laura</title>
  </programme>
  <programme start="20220330150000 -0600" stop="20220330160000 -0600" channel="Canal RTS">
    <title lang="es">Diseñando tu Amor</title>
  </programme>
  <programme start="20220330160000 -0600" stop="20220330170000 -0600" channel="Canal RTS">
    <title lang="es">Como dice el dicho</title>
  </programme>
  <programme start="20220330170000 -0600" stop="20220330180000 -0600" channel="Canal RTS">
    <title lang="es">Amar es primavera</title>
  </programme>
  <programme start="20220330180000 -0600" stop="20220330190000 -0600" channel="Canal RTS">
    <title lang="es">Las mil y una noches</title>
  </programme>
  <programme start="20220330190000 -0600" stop="20220330200000 -0600" channel="Canal RTS">
    <title lang="es">La Rosa de Guadalupe</title>
  </programme>
  <programme start="20220330200000 -0600" stop="20220330210000 -0600" channel="Canal RTS">
    <title lang="es">Elif</title>
  </programme>
  <programme start="20220330210000 -0600" stop="20220330220000 -0600" channel="Canal RTS">
    <title lang="es">Hercai</title>
  </programme>
  <programme start="20220330220000 -0600" stop="20220330230000 -0600" channel="Canal RTS">
    <title lang="es">La noticia</title>
  </programme>
  <programme start="20220330230000 -0600" stop="20220330231500 -0600" channel="Canal RTS">
    <title lang="es">Copa</title>
  </programme>
  <programme start="20220330010000 -0600" stop="20220330013000 -0600" channel="Canal GolTV Latinoamérica">
    <title lang="es">GOGOGOAL</title>
  </programme>
  <programme start="20220330013000 -0600" stop="20220330033000 -0600" channel="Canal GolTV Latinoamérica">
    <title lang="es">Mushuc Runa vs. Barcelona</title>
  </programme>
  <programme start="20220330033000 -0600" stop="20220330040000 -0600" channel="Canal GolTV Latinoamérica">
    <title lang="es">Tu Futbol Peru</title>
  </programme>
  <programme start="20220330040000 -0600" stop="20220330060000 -0600" channel="Canal GolTV Latinoamérica">
    <title lang="es">Boston River vs. Defensor Sporting</title>
  </programme>
  <programme start="20220330060000 -0600" stop="20220330080000 -0600" channel="Canal GolTV Latinoamérica">
    <title lang="es">AZ Alkmaar vs. Ajax</title>
  </programme>
  <programme start="20220330080000 -0600" stop="20220330090000 -0600" channel="Canal GolTV Latinoamérica">
    <title lang="es">Portugol</title>
  </programme>
  <programme start="20220330090000 -0600" stop="20220330110000 -0600" channel="Canal GolTV Latinoamérica">
    <title lang="es">Tondela vs. Arouca</title>
  </programme>
  <programme start="20220330110000 -0600" stop="20220330120000 -0600" channel="Canal GolTV Latinoamérica">
    <title lang="es">Fanáticos</title>
  </programme>
  <programme start="20220330120000 -0600" stop="20220330130000 -0600" channel="Canal GolTV Latinoamérica">
    <title lang="es">El Show del Fútbol</title>
  </programme>
  <programme start="20220330130000 -0600" stop="20220330140000 -0600" channel="Canal GolTV Latinoamérica">
    <title lang="es">GolNoticias</title>
  </programme>
  <programme start="20220330140000 -0600" stop="20220330143000 -0600" channel="Canal GolTV Latinoamérica">
    <title lang="es">The Football Review</title>
  </programme>
  <programme start="20220330143000 -0600" stop="20220330163000 -0600" channel="Canal GolTV Latinoamérica">
    <title lang="es">Deportivo Cuenca vs. Universidad Católica</title>
  </programme>
  <programme start="20220330163000 -0600" stop="20220330173000 -0600" channel="Canal GolTV Latinoamérica">
    <title lang="es">Portugol</title>
  </programme>
  <programme start="20220330173000 -0600" stop="20220330180000 -0600" channel="Canal GolTV Latinoamérica">
    <title lang="es">Tu Fútbol - Perú</title>
  </programme>
  <programme start="20220330180000 -0600" stop="20220330190000 -0600" channel="Canal GolTV Latinoamérica">
    <title lang="es">Fanáticos</title>
  </programme>
  <programme start="20220330190000 -0600" stop="20220330200000 -0600" channel="Canal GolTV Latinoamérica">
    <title lang="es">GolTV Noticias</title>
  </programme>
  <programme start="20220330200000 -0600" stop="20220330203000 -0600" channel="Canal GolTV Latinoamérica">
    <title lang="es">Tu Fútbol - Perú</title>
  </programme>
  <programme start="20220330203000 -0600" stop="20220330210000 -0600" channel="Canal GolTV Latinoamérica">
    <title lang="es">The Football Review</title>
  </programme>
  <programme start="20220330210000 -0600" stop="20220330220000 -0600" channel="Canal GolTV Latinoamérica">
    <title lang="es">Portugol</title>
  </programme>
  <programme start="20220330220000 -0600" stop="20220331000000 -0600" channel="Canal GolTV Latinoamérica">
    <title lang="es">Benfica vs. Estoril</title>
  </programme>
  <programme start="20220330014100 -0600" stop="20220330032500 -0600" channel="Canal Cinemax (México)">
    <title lang="es">Viene de Noche</title>
    <desc lang="es">Paul, tratando de proteger a su familia y amigos de los peligros que están afuera, pero no se imagina que adentro de su casa hay más peligro que afuera.(n)</desc>
    <credits>
      <actor>Joel Edgerton</actor>
      <actor>Christopher Abbott</actor>
      <actor>Carmen Ejogo</actor>
      <actor>Kelvin Harrison Jr.</actor>
      <actor>Riley Keough</actor>
      <actor>Griffin Robert Faulkner</actor>
      <actor>David Pendleton</actor>
      <actor>Mikey</actor>
      <producer>David Kaplan</producer>
      <producer>Andrea Roa</producer>
    </credits>
    <date>2017</date>
    <category lang="es">Película</category>
    <icon src="https://imagenes.gatotv.com/categorias/peliculas/miniatura/viene_de_noche.jpg" />
    <rating>
      <value>R</value>
    </rating>
  </programme>
  <programme start="20220330032500 -0600" stop="20220330050800 -0600" channel="Canal Cinemax (México)">
    <title lang="es">Ecos en la Oscuridad</title>
  </programme>
  <programme start="20220330050800 -0600" stop="20220330070000 -0600" channel="Canal Cinemax (México)">
    <title lang="es">No confíes en nadie</title>
  </programme>
  <programme start="20220330070000 -0600" stop="20220330092000 -0600" channel="Canal Cinemax (México)">
    <title lang="es">Pura suerte</title>
  </programme>
  <programme start="20220330092000 -0600" stop="20220330111800 -0600" channel="Canal Cinemax (México)">
    <title lang="es">La llave maestra</title>
  </programme>
  <programme start="20220330111800 -0600" stop="20220330132500 -0600" channel="Canal Cinemax (México)">
    <title lang="es">Secretos de Estado</title>
  </programme>
  <programme start="20220330132500 -0600" stop="20220330153000 -0600" channel="Canal Cinemax (México)">
    <title lang="es">Oblivion</title>
    <desc lang="es">Tom Cruise. Un reparador de drones del planeta tierra desvastado luego de décadas de guerras con los extraterrestres descubre los restos de una nave espacial.(n)</desc>
    <credits>
      <actor>Tom Cruise</actor>
      <actor>Morgan Freeman</actor>
      <actor>Olga Kurylenko</actor>
      <actor>Andrea Riseborough</actor>
      <producer>Joseph Kosinski</producer>
      <producer>Peter Chernin</producer>
    </credits>
    <date>2013</date>
    <category lang="es">Película</category>
    <icon src="https://imagenes.gatotv.com/categorias/peliculas/miniatura/oblivion_el_tiempo_del_olvido.jpg" />
    <rating>
      <value>PG-13</value>
    </rating>
  </programme>
  <programme start="20220330153000 -0600" stop="20220330172500 -0600" channel="Canal Cinemax (México)">
    <title lang="es">Intrusos</title>
  </programme>
  <programme start="20220330172500 -0600" stop="20220330195400 -0600" channel="Canal Cinemax (México)">
    <title lang="es">Tropa de Héroes</title>
    <title lang="xx">12 Strong</title>
    <desc lang="es">Después del 9/11 un equipo de fuerzas especiales estadounidenses y la alianza del norte, deben enfrentar a un enemigo despiadado que no toma prisioneros.(n)</desc>
    <credits>
      <actor>Chris Hemsworth</actor>
      <actor>Michael Shannon</actor>
      <actor>Michael Peña</actor>
      <actor>Navid Negahban</actor>
      <actor>Trevante Rhodes</actor>
      <actor>Elsa Pataky</actor>
      <actor>William Fichtner</actor>
      <actor>Rob Riggle</actor>
      <producer>Jerry Bruckheimer</producer>
      <producer>Molly Smith</producer>
      <composer>Lorne Balfe</composer>
    </credits>
    <date>2018</date>
    <category lang="es">Película</category>
    <icon src="https://imagenes.gatotv.com/categorias/peliculas/miniatura/12_strong.jpg" />
    <rating>
      <value>R</value>
    </rating>
  </programme>
  <programme start="20220330195400 -0600" stop="20220330220000 -0600" channel="Canal Cinemax (México)">
    <title lang="es">La ciudad de las tormentas</title>
  </programme>
  <programme start="20220330220000 -0600" stop="20220331000400 -0600" channel="Canal Cinemax (México)">
    <title lang="es">Oblivion</title>
    <desc lang="es">Tom Cruise. Un reparador de drones del planeta tierra desvastado luego de décadas de guerras con los extraterrestres descubre los restos de una nave espacial.(n)</desc>
    <credits>
      <actor>Tom Cruise</actor>
      <actor>Morgan Freeman</actor>
      <actor>Olga Kurylenko</actor>
      <actor>Andrea Riseborough</actor>
      <producer>Joseph Kosinski</producer>
      <producer>Peter Chernin</producer>
    </credits>
    <date>2013</date>
    <category lang="es">Película</category>
    <icon src="https://imagenes.gatotv.com/categorias/peliculas/miniatura/oblivion_el_tiempo_del_olvido.jpg" />
    <rating>
      <value>PG-13</value>
    </rating>
  </programme>
  <programme start="20220330005700 -0600" stop="20220330015200 -0600" channel="Canal National Geographic (Centro)">
    <title lang="es">Bios. Vidas que marcaron la tuya</title>
  </programme>
  <programme start="20220330015200 -0600" stop="20220330023700 -0600" channel="Canal National Geographic (Centro)">
    <title lang="es">Gordon Ramsay sabores extremos</title>
  </programme>
  <programme start="20220330023700 -0600" stop="20220330032000 -0600" channel="Canal National Geographic (Centro)">
    <title lang="es">Como lo hace la Tribú</title>
  </programme>
  <programme start="20220330032000 -0600" stop="20220330040200 -0600" channel="Canal National Geographic (Centro)">
    <title lang="es">Isla salvaje supervivencia en Alaska</title>
  </programme>
  <programme start="20220330040200 -0600" stop="20220330044500 -0600" channel="Canal National Geographic (Centro)">
    <title lang="es">Alerta Aeropuerto</title>
  </programme>
  <programme start="20220330044500 -0600" stop="20220330052700 -0600" channel="Canal National Geographic (Centro)">
    <title lang="es">Alerta Aeropuerto</title>
  </programme>
  <programme start="20220330052700 -0600" stop="20220330054700 -0600" channel="Canal National Geographic (Centro)">
    <title lang="es">Megaindustria de alimentos</title>
  </programme>
  <programme start="20220330054700 -0600" stop="20220330060700 -0600" channel="Canal National Geographic (Centro)">
    <title lang="es">Megaindustria de alimentos</title>
  </programme>
  <programme start="20220330060700 -0600" stop="20220330070000 -0600" channel="Canal National Geographic (Centro)">
    <title lang="es">Megaindustria de alimentos</title>
  </programme>
  <programme start="20220330070000 -0600" stop="20220330073000 -0600" channel="Canal National Geographic (Centro)">
    <title lang="es">Infomercial</title>
  </programme>
  <programme start="20220330073000 -0600" stop="20220330080000 -0600" channel="Canal National Geographic (Centro)">
    <title lang="es">Infomercial</title>
  </programme>
  <programme start="20220330080000 -0600" stop="20220330083000 -0600" channel="Canal National Geographic (Centro)">
    <title lang="es">Infomercial</title>
  </programme>
  <programme start="20220330083000 -0600" stop="20220330090000 -0600" channel="Canal National Geographic (Centro)">
    <title lang="es">Infomercial</title>
  </programme>
  <programme start="20220330090000 -0600" stop="20220330093000 -0600" channel="Canal National Geographic (Centro)">
    <title lang="es">Infomercial</title>
  </programme>
  <programme start="20220330093000 -0600" stop="20220330100000 -0600" channel="Canal National Geographic (Centro)">
    <title lang="es">Infomercial</title>
  </programme>
  <programme start="20220330100000 -0600" stop="20220330103000 -0600" channel="Canal National Geographic (Centro)">
    <title lang="es">Infomercial</title>
  </programme>
  <programme start="20220330103000 -0600" stop="20220330110000 -0600" channel="Canal National Geographic (Centro)">
    <title lang="es">Infomercial</title>
  </programme>
  <programme start="20220330110000 -0600" stop="20220330113000 -0600" channel="Canal National Geographic (Centro)">
    <title lang="es">Megaindustria de alimentos</title>
  </programme>
  <programme start="20220330113000 -0600" stop="20220330120000 -0600" channel="Canal National Geographic (Centro)">
    <title lang="es">Megaindustria de alimentos</title>
  </programme>
  <programme start="20220330120000 -0600" stop="20220330123000 -0600" channel="Canal National Geographic (Centro)">
    <title lang="es">Megaindustria de alimentos</title>
  </programme>
  <programme start="20220330123000 -0600" stop="20220330133700 -0600" channel="Canal National Geographic (Centro)">
    <title lang="es">Reconstrucciones Asombrosas</title>
  </programme>
  <programme start="20220330133700 -0600" stop="20220330143200 -0600" channel="Canal National Geographic (Centro)">
    <title lang="es">Tormentas Implacables</title>
  </programme>
  <programme start="20220330143200 -0600" stop="20220330152700 -0600" channel="Canal National Geographic (Centro)">
    <title lang="es">Patrullas de Alaska</title>
  </programme>
  <programme start="20220330152700 -0600" stop="20220330162200 -0600" channel="Canal National Geographic (Centro)">
    <title lang="es">Serpientes en la ciudad</title>
  </programme>
  <programme start="20220330162200 -0600" stop="20220330171700 -0600" channel="Canal National Geographic (Centro)">
    <title lang="es">El club de la pelea animal</title>
  </programme>
  <programme start="20220330171700 -0600" stop="20220330181200 -0600" channel="Canal National Geographic (Centro)">
    <title lang="es">Preso en el extranjero crimen y castigo</title>
  </programme>
  <programme start="20220330181200 -0600" stop="20220330190700 -0600" channel="Canal National Geographic (Centro)">
    <title lang="es">Tesoros Perdidos de Egipto</title>
  </programme>
  <programme start="20220330190700 -0600" stop="20220330200500 -0600" channel="Canal National Geographic (Centro)">
    <title lang="es">Revelaciones del antiguo Egipto</title>
  </programme>
  <programme start="20220330200500 -0600" stop="20220330210000 -0600" channel="Canal National Geographic (Centro)">
    <title lang="es">Tutankamón a Color</title>
  </programme>
  <programme start="20220330210000 -0600" stop="20220330215500 -0600" channel="Canal National Geographic (Centro)">
    <title lang="es">Alerta Aeropuerto</title>
  </programme>
  <programme start="20220330215500 -0600" stop="20220330225000 -0600" channel="Canal National Geographic (Centro)">
    <title lang="es">Mayday Catastrofes aereas</title>
  </programme>
  <programme start="20220330225000 -0600" stop="20220330235200 -0600" channel="Canal National Geographic (Centro)">
    <title lang="es">Tragedias aéreas recreadas</title>
  </programme>
  <programme start="20220330235200 -0600" stop="20220331015700 -0600" channel="Canal National Geographic (Centro)">
    <title lang="es">Bios. Vidas que marcaron la tuya</title>
  </programme>
  <programme start="20220330003000 -0600" stop="20220330013000 -0600" channel="Canal ESPN 2 (Colombia)">
    <title lang="es">SportsCenter</title>
    <desc lang="es">El noticiero deportivo de la cadena ESPN el cual muestra los acontecimientos más importantes del deporte incluyendo resúmenes y marcadores.(n)</desc>
    <category lang="es">Fútbol Americano</category>
    <category lang="es">Baloncesto</category>
    <category lang="es">Béisbol</category>
    <category lang="es">Básquetbol</category>
    <category lang="es">Fútbol Italiano</category>
    <category lang="es">Major League Baseball</category>
    <category lang="es">Fútbol Mexicano</category>
    <category lang="es">MLB</category>
    <category lang="es">NBA</category>
    <category lang="es">Noticias</category>
    <category lang="es">NFL</category>
    <category lang="es">Fútbol</category>
    <category lang="es">UEFA</category>
    <category lang="es">Fútbol Español</category>
    <icon src="https://imagenes.gatotv.com/categorias/noticieros/miniatura/sportscenter.png" />
  </programme>
  <programme start="20220330013000 -0600" stop="20220330023000 -0600" channel="Canal ESPN 2 (Colombia)">
    <title lang="es">SportsCenter</title>
    <desc lang="es">El noticiero deportivo de la cadena ESPN el cual muestra los acontecimientos más importantes del deporte incluyendo resúmenes y marcadores.(n)</desc>
    <category lang="es">Fútbol Americano</category>
    <category lang="es">Baloncesto</category>
    <category lang="es">Béisbol</category>
    <category lang="es">Básquetbol</category>
    <category lang="es">Fútbol Italiano</category>
    <category lang="es">Major League Baseball</category>
    <category lang="es">Fútbol Mexicano</category>
    <category lang="es">MLB</category>
    <category lang="es">NBA</category>
    <category lang="es">Noticias</category>
    <category lang="es">NFL</category>
    <category lang="es">Fútbol</category>
    <category lang="es">UEFA</category>
    <category lang="es">Fútbol Español</category>
    <icon src="https://imagenes.gatotv.com/categorias/noticieros/miniatura/sportscenter.png" />
  </programme>
  <programme start="20220330023000 -0600" stop="20220330030000 -0600" channel="Canal ESPN 2 (Colombia)">
    <title lang="es">ESPN Run</title>
  </programme>
  <programme start="20220330030000 -0600" stop="20220330033000 -0600" channel="Canal ESPN 2 (Colombia)">
    <title lang="es">ESPN Yoga</title>
  </programme>
  <programme start="20220330033000 -0600" stop="20220330040000 -0600" channel="Canal ESPN 2 (Colombia)">
    <title lang="es">ESPN X</title>
  </programme>
  <programme start="20220330040000 -0600" stop="20220330060000 -0600" channel="Canal ESPN 2 (Colombia)">
    <title lang="es">Equipo F</title>
  </programme>
  <programme start="20220330060000 -0600" stop="20220330063000 -0600" channel="Canal ESPN 2 (Colombia)">
    <title lang="es">Aguas arriba</title>
  </programme>
  <programme start="20220330063000 -0600" stop="20220330070000 -0600" channel="Canal ESPN 2 (Colombia)">
    <title lang="es">ESPN W</title>
  </programme>
  <programme start="20220330070000 -0600" stop="20220330080000 -0600" channel="Canal ESPN 2 (Colombia)">
    <title lang="es">El show de la F1</title>
  </programme>
  <programme start="20220330080000 -0600" stop="20220330090000 -0600" channel="Canal ESPN 2 (Colombia)">
    <title lang="es">ESPN Compact - ATP Masters 1000 - Miami</title>
  </programme>
  <programme start="20220330090000 -0600" stop="20220330100000 -0600" channel="Canal ESPN 2 (Colombia)">
    <title lang="es">ESPN Compact - ATP Masters 1000 - Miami</title>
  </programme>
  <programme start="20220330100000 -0600" stop="20220330103000 -0600" channel="Canal ESPN 2 (Colombia)">
    <title lang="es">ESPN Yoga</title>
  </programme>
  <programme start="20220330103000 -0600" stop="20220330110000 -0600" channel="Canal ESPN 2 (Colombia)">
    <title lang="es">ESPN W</title>
  </programme>
  <programme start="20220330110000 -0600" stop="20220330120000 -0600" channel="Canal ESPN 2 (Colombia)">
    <title lang="es">Fútbol Eliminatorias Copa Mundial de la FIFA Catar 2022</title>
  </programme>
  <programme start="20220330120000 -0600" stop="20220330130000 -0600" channel="Canal ESPN 2 (Colombia)">
    <title lang="es">ESPN Compact - Eliminatorias Qatar 2022</title>
  </programme>
  <programme start="20220330130000 -0600" stop="20220330140000 -0600" channel="Canal ESPN 2 (Colombia)">
    <title lang="es">PGA Tour Highlights - World Golf Championship - Dell Technologies Match Play</title>
  </programme>
  <programme start="20220330140000 -0600" stop="20220330170000 -0600" channel="Canal ESPN 2 (Colombia)">
    <title lang="es">SportsCenter+</title>
  </programme>
  <programme start="20220330170000 -0600" stop="20220330183000 -0600" channel="Canal ESPN 2 (Colombia)">
    <title lang="es">SportsCenter</title>
    <desc lang="es">El noticiero deportivo de la cadena ESPN el cual muestra los acontecimientos más importantes del deporte incluyendo resúmenes y marcadores.(n)</desc>
    <category lang="es">Fútbol Americano</category>
    <category lang="es">Baloncesto</category>
    <category lang="es">Béisbol</category>
    <category lang="es">Básquetbol</category>
    <category lang="es">Fútbol Italiano</category>
    <category lang="es">Major League Baseball</category>
    <category lang="es">Fútbol Mexicano</category>
    <category lang="es">MLB</category>
    <category lang="es">NBA</category>
    <category lang="es">Noticias</category>
    <category lang="es">NFL</category>
    <category lang="es">Fútbol</category>
    <category lang="es">UEFA</category>
    <category lang="es">Fútbol Español</category>
    <icon src="https://imagenes.gatotv.com/categorias/noticieros/miniatura/sportscenter.png" />
  </programme>
  <programme start="20220330183000 -0600" stop="20220330210000 -0600" channel="Canal ESPN 2 (Colombia)">
    <title lang="es">Baloncesto de la NBA</title>
  </programme>
  <programme start="20220330210000 -0600" stop="20220330233000 -0600" channel="Canal ESPN 2 (Colombia)">
    <title lang="es">Baloncesto de la NBA</title>
  </programme>
  <programme start="20220330233000 -0600" stop="20220331000000 -0600" channel="Canal ESPN 2 (Colombia)">
    <title lang="es">ESPN Ciclismo</title>
  </programme>
  <programme start="20220330012900 -0600" stop="20220330015300 -0600" channel="Canal Warner TV (Panregional)">
    <title lang="es">Dragon Ball Super</title>
  </programme>
  <programme start="20220330015300 -0600" stop="20220330021700 -0600" channel="Canal Warner TV (Panregional)">
    <title lang="es">Dragon Ball Super</title>
  </programme>
  <programme start="20220330021700 -0600" stop="20220330030500 -0600" channel="Canal Warner TV (Panregional)">
    <title lang="es">Rescue me</title>
  </programme>
  <programme start="20220330030500 -0600" stop="20220330032600 -0600" channel="Canal Warner TV (Panregional)">
    <title lang="es">The Big Bang Theory</title>
    <desc lang="es">La vida de dos brillantes pero socialmente inadaptados físicos esta por cambiar cuando una hermosa vecina llega al edificio de apartamentos de estos.(n)</desc>
    <credits>
      <actor>Johnny Galecki</actor>
      <actor>Jim Parsons</actor>
      <actor>Kaley Cuoco</actor>
      <actor>Simon Helberg</actor>
      <actor>Kunal Nayyar</actor>
      <actor>Sara Gilbert</actor>
      <actor>Melissa Rauch</actor>
      <actor>Mayim Bialik</actor>
    </credits>
    <date>2007</date>
    <icon src="https://imagenes.gatotv.com/categorias/programas/miniatura/the_big_bang_theory.jpg" />
    <rating>
      <value>TV-14</value>
    </rating>
  </programme>
  <programme start="20220330032600 -0600" stop="20220330034600 -0600" channel="Canal Warner TV (Panregional)">
    <title lang="es">The Big Bang Theory</title>
    <desc lang="es">La vida de dos brillantes pero socialmente inadaptados físicos esta por cambiar cuando una hermosa vecina llega al edificio de apartamentos de estos.(n)</desc>
    <credits>
      <actor>Johnny Galecki</actor>
      <actor>Jim Parsons</actor>
      <actor>Kaley Cuoco</actor>
      <actor>Simon Helberg</actor>
      <actor>Kunal Nayyar</actor>
      <actor>Sara Gilbert</actor>
      <actor>Melissa Rauch</actor>
      <actor>Mayim Bialik</actor>
    </credits>
    <date>2007</date>
    <icon src="https://imagenes.gatotv.com/categorias/programas/miniatura/the_big_bang_theory.jpg" />
    <rating>
      <value>TV-14</value>
    </rating>
  </programme>
  <programme start="20220330034600 -0600" stop="20220330040600 -0600" channel="Canal Warner TV (Panregional)">
    <title lang="es">The Big Bang Theory</title>
    <desc lang="es">La vida de dos brillantes pero socialmente inadaptados físicos esta por cambiar cuando una hermosa vecina llega al edificio de apartamentos de estos.(n)</desc>
    <credits>
      <actor>Johnny Galecki</actor>
      <actor>Jim Parsons</actor>
      <actor>Kaley Cuoco</actor>
      <actor>Simon Helberg</actor>
      <actor>Kunal Nayyar</actor>
      <actor>Sara Gilbert</actor>
      <actor>Melissa Rauch</actor>
      <actor>Mayim Bialik</actor>
    </credits>
    <date>2007</date>
    <icon src="https://imagenes.gatotv.com/categorias/programas/miniatura/the_big_bang_theory.jpg" />
    <rating>
      <value>TV-14</value>
    </rating>
  </programme>
  <programme start="20220330040600 -0600" stop="20220330042700 -0600" channel="Canal Warner TV (Panregional)">
    <title lang="es">The Big Bang Theory</title>
    <desc lang="es">La vida de dos brillantes pero socialmente inadaptados físicos esta por cambiar cuando una hermosa vecina llega al edificio de apartamentos de estos.(n)</desc>
    <credits>
      <actor>Johnny Galecki</actor>
      <actor>Jim Parsons</actor>
      <actor>Kaley Cuoco</actor>
      <actor>Simon Helberg</actor>
      <actor>Kunal Nayyar</actor>
      <actor>Sara Gilbert</actor>
      <actor>Melissa Rauch</actor>
      <actor>Mayim Bialik</actor>
    </credits>
    <date>2007</date>
    <icon src="https://imagenes.gatotv.com/categorias/programas/miniatura/the_big_bang_theory.jpg" />
    <rating>
      <value>TV-14</value>
    </rating>
  </programme>
  <programme start="20220330042700 -0600" stop="20220330044700 -0600" channel="Canal Warner TV (Panregional)">
    <title lang="es">The Big Bang Theory</title>
    <desc lang="es">La vida de dos brillantes pero socialmente inadaptados físicos esta por cambiar cuando una hermosa vecina llega al edificio de apartamentos de estos.(n)</desc>
    <credits>
      <actor>Johnny Galecki</actor>
      <actor>Jim Parsons</actor>
      <actor>Kaley Cuoco</actor>
      <actor>Simon Helberg</actor>
      <actor>Kunal Nayyar</actor>
      <actor>Sara Gilbert</actor>
      <actor>Melissa Rauch</actor>
      <actor>Mayim Bialik</actor>
    </credits>
    <date>2007</date>
    <icon src="https://imagenes.gatotv.com/categorias/programas/miniatura/the_big_bang_theory.jpg" />
    <rating>
      <value>TV-14</value>
    </rating>
  </programme>
  <programme start="20220330044700 -0600" stop="20220330060000 -0600" channel="Canal Warner TV (Panregional)">
    <title lang="es">Warner Series Block</title>
  </programme>
  <programme start="20220330060000 -0600" stop="20220330072300 -0600" channel="Canal Warner TV (Panregional)">
    <title lang="es">Warner Series Block</title>
  </programme>
  <programme start="20220330072300 -0600" stop="20220330074300 -0600" channel="Canal Warner TV (Panregional)">
    <title lang="es">The Big Bang Theory</title>
    <desc lang="es">La vida de dos brillantes pero socialmente inadaptados físicos esta por cambiar cuando una hermosa vecina llega al edificio de apartamentos de estos.(n)</desc>
    <credits>
      <actor>Johnny Galecki</actor>
      <actor>Jim Parsons</actor>
      <actor>Kaley Cuoco</actor>
      <actor>Simon Helberg</actor>
      <actor>Kunal Nayyar</actor>
      <actor>Sara Gilbert</actor>
      <actor>Melissa Rauch</actor>
      <actor>Mayim Bialik</actor>
    </credits>
    <date>2007</date>
    <icon src="https://imagenes.gatotv.com/categorias/programas/miniatura/the_big_bang_theory.jpg" />
    <rating>
      <value>TV-14</value>
    </rating>
  </programme>
  <programme start="20220330074300 -0600" stop="20220330080400 -0600" channel="Canal Warner TV (Panregional)">
    <title lang="es">The Big Bang Theory</title>
    <desc lang="es">La vida de dos brillantes pero socialmente inadaptados físicos esta por cambiar cuando una hermosa vecina llega al edificio de apartamentos de estos.(n)</desc>
    <credits>
      <actor>Johnny Galecki</actor>
      <actor>Jim Parsons</actor>
      <actor>Kaley Cuoco</actor>
      <actor>Simon Helberg</actor>
      <actor>Kunal Nayyar</actor>
      <actor>Sara Gilbert</actor>
      <actor>Melissa Rauch</actor>
      <actor>Mayim Bialik</actor>
    </credits>
    <date>2007</date>
    <icon src="https://imagenes.gatotv.com/categorias/programas/miniatura/the_big_bang_theory.jpg" />
    <rating>
      <value>TV-14</value>
    </rating>
  </programme>
  <programme start="20220330080400 -0600" stop="20220330082800 -0600" channel="Canal Warner TV (Panregional)">
    <title lang="es">The Big Bang Theory</title>
    <desc lang="es">La vida de dos brillantes pero socialmente inadaptados físicos esta por cambiar cuando una hermosa vecina llega al edificio de apartamentos de estos.(n)</desc>
    <credits>
      <actor>Johnny Galecki</actor>
      <actor>Jim Parsons</actor>
      <actor>Kaley Cuoco</actor>
      <actor>Simon Helberg</actor>
      <actor>Kunal Nayyar</actor>
      <actor>Sara Gilbert</actor>
      <actor>Melissa Rauch</actor>
      <actor>Mayim Bialik</actor>
    </credits>
    <date>2007</date>
    <icon src="https://imagenes.gatotv.com/categorias/programas/miniatura/the_big_bang_theory.jpg" />
    <rating>
      <value>TV-14</value>
    </rating>
  </programme>
  <programme start="20220330082800 -0600" stop="20220330085000 -0600" channel="Canal Warner TV (Panregional)">
    <title lang="es">The Big Bang Theory</title>
    <desc lang="es">La vida de dos brillantes pero socialmente inadaptados físicos esta por cambiar cuando una hermosa vecina llega al edificio de apartamentos de estos.(n)</desc>
    <credits>
      <actor>Johnny Galecki</actor>
      <actor>Jim Parsons</actor>
      <actor>Kaley Cuoco</actor>
      <actor>Simon Helberg</actor>
      <actor>Kunal Nayyar</actor>
      <actor>Sara Gilbert</actor>
      <actor>Melissa Rauch</actor>
      <actor>Mayim Bialik</actor>
    </credits>
    <date>2007</date>
    <icon src="https://imagenes.gatotv.com/categorias/programas/miniatura/the_big_bang_theory.jpg" />
    <rating>
      <value>TV-14</value>
    </rating>
  </programme>
  <programme start="20220330085000 -0600" stop="20220330090900 -0600" channel="Canal Warner TV (Panregional)">
    <title lang="es">The Big Bang Theory</title>
    <desc lang="es">La vida de dos brillantes pero socialmente inadaptados físicos esta por cambiar cuando una hermosa vecina llega al edificio de apartamentos de estos.(n)</desc>
    <credits>
      <actor>Johnny Galecki</actor>
      <actor>Jim Parsons</actor>
      <actor>Kaley Cuoco</actor>
      <actor>Simon Helberg</actor>
      <actor>Kunal Nayyar</actor>
      <actor>Sara Gilbert</actor>
      <actor>Melissa Rauch</actor>
      <actor>Mayim Bialik</actor>
    </credits>
    <date>2007</date>
    <icon src="https://imagenes.gatotv.com/categorias/programas/miniatura/the_big_bang_theory.jpg" />
    <rating>
      <value>TV-14</value>
    </rating>
  </programme>
  <programme start="20220330090900 -0600" stop="20220330093100 -0600" channel="Canal Warner TV (Panregional)">
    <title lang="es">The Big Bang Theory</title>
    <desc lang="es">La vida de dos brillantes pero socialmente inadaptados físicos esta por cambiar cuando una hermosa vecina llega al edificio de apartamentos de estos.(n)</desc>
    <credits>
      <actor>Johnny Galecki</actor>
      <actor>Jim Parsons</actor>
      <actor>Kaley Cuoco</actor>
      <actor>Simon Helberg</actor>
      <actor>Kunal Nayyar</actor>
      <actor>Sara Gilbert</actor>
      <actor>Melissa Rauch</actor>
      <actor>Mayim Bialik</actor>
    </credits>
    <date>2007</date>
    <icon src="https://imagenes.gatotv.com/categorias/programas/miniatura/the_big_bang_theory.jpg" />
    <rating>
      <value>TV-14</value>
    </rating>
  </programme>
  <programme start="20220330093100 -0600" stop="20220330095500 -0600" channel="Canal Warner TV (Panregional)">
    <title lang="es">Brooklyn nine-nine</title>
  </programme>
  <programme start="20220330095500 -0600" stop="20220330101900 -0600" channel="Canal Warner TV (Panregional)">
    <title lang="es">Brooklyn nine-nine</title>
  </programme>
  <programme start="20220330101900 -0600" stop="20220330104200 -0600" channel="Canal Warner TV (Panregional)">
    <title lang="es">Dragon Ball Super</title>
  </programme>
  <programme start="20220330104200 -0600" stop="20220330110600 -0600" channel="Canal Warner TV (Panregional)">
    <title lang="es">Dragon Ball Super</title>
  </programme>
  <programme start="20220330110600 -0600" stop="20220330122500 -0600" channel="Canal Warner TV (Panregional)">
    <title lang="es">Amigos salvajes 2</title>
  </programme>
  <programme start="20220330122500 -0600" stop="20220330135000 -0600" channel="Canal Warner TV (Panregional)">
    <title lang="es">Amigos salvajes 3</title>
  </programme>
  <programme start="20220330135000 -0600" stop="20220330155100 -0600" channel="Canal Warner TV (Panregional)">
    <title lang="es">Linterna verde</title>
  </programme>
  <programme start="20220330155100 -0600" stop="20220330161200 -0600" channel="Canal Warner TV (Panregional)">
    <title lang="es">Brooklyn nine-nine</title>
  </programme>
  <programme start="20220330161200 -0600" stop="20220330163500 -0600" channel="Canal Warner TV (Panregional)">
    <title lang="es">Brooklyn nine-nine</title>
  </programme>
  <programme start="20220330163500 -0600" stop="20220330170200 -0600" channel="Canal Warner TV (Panregional)">
    <title lang="es">Dragon Ball Super</title>
  </programme>
  <programme start="20220330170200 -0600" stop="20220330172800 -0600" channel="Canal Warner TV (Panregional)">
    <title lang="es">Dragon Ball Super</title>
  </programme>
  <programme start="20220330172800 -0600" stop="20220330192500 -0600" channel="Canal Warner TV (Panregional)">
    <title lang="es">De la cuna a la tumba</title>
  </programme>
  <programme start="20220330192500 -0600" stop="20220330220000 -0600" channel="Canal Warner TV (Panregional)">
    <title lang="es">Los Juegos del Hambre</title>
    <desc lang="es">Panem elije participantes de doce distritos, cada distrito aporta 2 participantes eligiéndolos como tributo.(n)</desc>
    <credits>
      <actor>Jennifer Lawrence</actor>
      <actor>Josh Hutcherson</actor>
      <actor>Liam Hemsworth</actor>
      <actor>Woody Harrelson</actor>
      <actor>Elizabeth Banks</actor>
      <actor>Lenny Kravitz</actor>
      <actor>Stanley Tucci</actor>
      <actor>Donald Sutherland</actor>
      <producer>Jon Kilik</producer>
      <producer>Nina Jacobson</producer>
      <composer>James Newton Howard</composer>
    </credits>
    <date>2012</date>
    <category lang="es">Película</category>
    <icon src="https://imagenes.gatotv.com/categorias/peliculas/miniatura/los_juegos_del_hambre.jpg" />
    <rating>
      <value>PG-13</value>
    </rating>
  </programme>
  <programme start="20220330220000 -0600" stop="20220331000600 -0600" channel="Canal Warner TV (Panregional)">
    <title lang="es">Terminator: La Salvación</title>
    <title lang="xx">Terminator Salvation</title>
    <desc lang="es">En el 2018, una misteriosa arma en la guerra contra las máquinas – mitad humano y mitad máquina – busca a John Connor para ayudar con la misión de atacar a Skynet.(n)</desc>
    <credits>
      <actor>Christian Bale</actor>
      <actor>Sam Worthington</actor>
      <producer>Derek Anderson</producer>
      <producer>Moritz Borman</producer>
      <composer>Danny Elfman</composer>
    </credits>
    <date>2009</date>
    <icon src="https://imagenes.gatotv.com/categorias/peliculas/miniatura/terminator_la_salvacion.jpg" />
    <country lang="es">Estados Unidos</country>
    <country lang="es">Reino Unido</country>
    <rating>
      <value>PG-13</value>
    </rating>
  </programme>
  <programme start="20220330010000 +0000" stop="20220330020000 +0000" channel="EC DIRECTV Sports Ecuador">
    <title lang="en">De ciclismo se habla así</title>
    <desc lang="en">La información del programa no fue provista por el proveedor de la señal.(n)</desc>
  </programme>
  <programme start="20220330020000 +0000" stop="20220330023000 +0000" channel="EC DIRECTV Sports Ecuador">
    <title lang="en">The FIFA World Cup Qatar 2022 monthly magazine</title>
    <desc lang="en">Una mirada a la cultura y tradiciones de Qatar y el desarrollo de los estadios que se preparan para albergar la Copa Mundial de la FIFA 2022. Además, el camino a la clasificación de las selecciones que buscan un lugar en la mayor cita mundial.(n)</desc>
  </programme>
  <programme start="20220330023000 +0000" stop="20220330030000 +0000" channel="EC DIRECTV Sports Ecuador">
    <title lang="en">UEFA European Qualifiers Highlights - FM Highlights Md11 Mn2</title>
    <desc lang="en">Resumen con los mejores momentos de los partidos clasificatorios en Europa.(n)</desc>
  </programme>
  <programme start="20220330030000 +0000" stop="20220330043000 +0000" channel="EC DIRECTV Sports Ecuador">
    <title lang="en">Debate Fútbol Ecuador</title>
    <desc lang="en">Un programa donde se debaten los temas más importantes del fútbol ecuatoriano, de una manera ágil y profesional. Con los mejores periodistas deportivos del país.(n)</desc>
    <icon src="https://d5ip5p2ldkpmf.cloudfront.net/cinema/DB_Photos/ShowCards/AllMADPhotos/15285757/p15285757_b_v5_v17_cmd2.jpg" />
    <premiere />
  </programme>
  <programme start="20220330043000 +0000" stop="20220330053000 +0000" channel="EC DIRECTV Sports Ecuador">
    <title lang="en">De fútbol se habla así, en Sudamérica</title>
    <desc lang="en">Este programa analizará todas las fechas de la Copa Sudamericana de forma exhaustiva, así como también focalizará en la actualidad de cada una de las selecciones sudamericanas y las competencias más relevantes.(n)</desc>
  </programme>
  <programme start="20220330053000 +0000" stop="20220330060000 +0000" channel="EC DIRECTV Sports Ecuador">
    <title lang="en">Todo en 30</title>
    <desc lang="en">En treinta minutos repaso de los mejores eventos deportivos. Lo más destacado de fútbol, básquet, tenis y todos los eventos que se transmitan en la pantalla de DirecTV Sports.(n)</desc>
  </programme>
  <programme start="20220330060000 +0000" stop="20220330070000 +0000" channel="EC DIRECTV Sports Ecuador">
    <title lang="en">Conexión DIRECTV</title>
    <desc lang="en">El noticiero deportivo más completo de la región con la actualidad de cada disciplina y las novedades de las ligas más importantes del planeta. La información al instante y la palabra de los protagonistas en primera persona.(n)</desc>
  </programme>
  <programme start="20220330070000 +0000" stop="20220330090000 +0000" channel="EC DIRECTV Sports Ecuador">
    <title lang="en">Irlanda vs. Bélgica : Fútbol - Irlanda vs. Bélgica</title>
    <desc lang="en">Amistoso internacional. Irlanda enfrenta a Bélgica en el Estadio Aviva de Dublín.(n)</desc>
  </programme>
  <programme start="20220330090000 +0000" stop="20220330110000 +0000" channel="EC DIRECTV Sports Ecuador">
    <title lang="en">Francia vs. Sudáfrica : Fútbol - Francia vs. Sudáfrica</title>
    <desc lang="en">Amistoso internacional. Francia enfrenta a Sudáfrica en el Estadio Pierre-Mauroy.(n)</desc>
  </programme>
  <programme start="20220330110000 +0000" stop="20220330120000 +0000" channel="EC DIRECTV Sports Ecuador">
    <title lang="en">Conexión DIRECTV</title>
    <desc lang="en">El noticiero deportivo más completo de la región con la actualidad de cada disciplina y las novedades de las ligas más importantes del planeta. La información al instante y la palabra de los protagonistas en primera persona.(n)</desc>
  </programme>
  <programme start="20220330120000 +0000" stop="20220330140000 +0000" channel="EC DIRECTV Sports Ecuador">
    <title lang="en">Inglaterra vs. Costa de Marfil : Fútbol - Inglaterra vs. Costa de Marfil</title>
    <desc lang="en">Amistoso internacional. Inglaterra enfrenta a Costa de Marfil en el Estadio Wembley.(n)</desc>
  </programme>
  <programme start="20220330140000 +0000" stop="20220330143000 +0000" channel="EC DIRECTV Sports Ecuador">
    <title lang="en">Todo en 30</title>
    <desc lang="en">En treinta minutos repaso de los mejores eventos deportivos. Lo más destacado de fútbol, básquet, tenis y todos los eventos que se transmitan en la pantalla de DirecTV Sports.(n)</desc>
  </programme>
  <programme start="20220330143000 +0000" stop="20220330160000 +0000" channel="EC DIRECTV Sports Ecuador">
    <title lang="en">Debate Fútbol Ecuador</title>
    <desc lang="en">Un programa donde se debaten los temas más importantes del fútbol ecuatoriano, de una manera ágil y profesional. Con los mejores periodistas deportivos del país.(n)</desc>
    <icon src="https://d5ip5p2ldkpmf.cloudfront.net/cinema/DB_Photos/ShowCards/AllMADPhotos/15285757/p15285757_b_v5_v3_cmd2.jpg" />
  </programme>
  <programme start="20220330160000 +0000" stop="20220330163000 +0000" channel="EC DIRECTV Sports Ecuador">
    <title lang="en">The FIFA World Cup Qatar 2022 monthly magazine</title>
    <desc lang="en">Una mirada a la cultura y tradiciones de Qatar y el desarrollo de los estadios que se preparan para albergar la Copa Mundial de la FIFA 2022. Además, el camino a la clasificación de las selecciones que buscan un lugar en la mayor cita mundial.(n)</desc>
  </programme>
  <programme start="20220330163000 +0000" stop="20220330170000 +0000" channel="EC DIRECTV Sports Ecuador">
    <title lang="en">Ranking DIRECTV Sports</title>
    <desc lang="en">Relato de jugadas, eventos más destacados y las noticias del día contadas desde un costado humorístico y desfachatado. Todos los bloopers, los mejores goles, las burradas, y mucho más.(n)</desc>
    <icon src="https://d5ip5p2ldkpmf.cloudfront.net/cinema/DB_Photos/ShowCards/AllMADPhotos/17402206/p17402206_b_v5_v1_cmd2.jpg" />
  </programme>
  <programme start="20220330170000 +0000" stop="20220330180000 +0000" channel="EC DIRECTV Sports Ecuador">
    <title lang="en">Conexión DIRECTV</title>
    <desc lang="en">El noticiero deportivo más completo de la región con la actualidad de cada disciplina y las novedades de las ligas más importantes del planeta. La información al instante y la palabra de los protagonistas en primera persona.(n)</desc>
    <premiere />
  </programme>
  <programme start="20220330180000 +0000" stop="20220330190000 +0000" channel="EC DIRECTV Sports Ecuador">
    <title lang="en">El juego</title>
    <desc lang="en">Fernando Petrocelli y un grupo de destacados periodistas, representantes de cada país, integran este ciclo que tiene como misión informar sobre las ligas locales y mostrar lo más destacado de todos los eventos CONMEBOL.(n)</desc>
    <premiere />
  </programme>
  <programme start="20220330190000 +0000" stop="20220330210000 +0000" channel="EC DIRECTV Sports Ecuador">
    <title lang="en">Portugal vs. Macedonia : FIFA Eliminatorias Copa Mundial 2022 - Portugal vs. Macedonia</title>
    <desc lang="en">Final del repechaje por la clasificación. Portugal recibe a Macedonia del Norte en Oporto. Los lusos vienen de superar a Turquía por 3-1 y buscan su quinta participación mundialista. Los balcánicos, que nunca lo jugaron, vienen de eliminar a Italia.(n)</desc>
  </programme>
  <programme start="20220330210000 +0000" stop="20220330220000 +0000" channel="EC DIRECTV Sports Ecuador">
    <title lang="en">Real Madrid TV</title>
    <desc lang="en">Información del equipo, entrevistas, reportajes, noticias y resúmenes de los partidos. Análisis y debate sobre todas las competiciones tanto de la sección de fútbol como de la de baloncesto.(n)</desc>
  </programme>
  <programme start="20220330220000 +0000" stop="20220330233000 +0000" channel="EC DIRECTV Sports Ecuador">
    <title lang="en">Fútbol Total</title>
    <desc lang="en">Fútbol Total es el show futbolero más divertido de América Latina. El gran plantel de profesionales informa y analiza con un toque de humor las novedades de las ligas más relevantes del mundo.(n)</desc>
    <premiere />
  </programme>
  <programme start="20220330233000 +0000" stop="20220331000000 +0000" channel="EC DIRECTV Sports Ecuador">
    <title lang="en">Todo en 30</title>
    <desc lang="en">En treinta minutos repaso de los mejores eventos deportivos. Lo más destacado de fútbol, básquet, tenis y todos los eventos que se transmitan en la pantalla de DirecTV Sports.(n)</desc>
  </programme>
  <programme start="20220330010000 +0000" stop="20220330030000 +0000" channel="EC DIRECTV Sports 2">
    <title lang="en">Portugal vs. Macedonia : FIFA Eliminatorias Copa Mundial 2022 - Portugal vs. Macedonia</title>
    <desc lang="en">Final del repechaje por la clasificación. Portugal recibe a Macedonia del Norte en Oporto. Los lusos vienen de superar a Turquía por 3-1 y buscan su quinta participación mundialista. Los balcánicos, que nunca lo jugaron, vienen de eliminar a Italia.(n)</desc>
  </programme>
  <programme start="20220330030000 +0000" stop="20220330050000 +0000" channel="EC DIRECTV Sports 2">
    <title lang="en">El chiringuito de jugones</title>
    <desc lang="en">Programa deportivo en el que se trata toda la información y las noticias más importantes acerca de los equipos de fútbol español. Ocho tertulianos aportarán su punto de vista sobre los temas a tratar.(n)</desc>
  </programme>
  <programme start="20220330050000 +0000" stop="20220330053000 +0000" channel="EC DIRECTV Sports 2">
    <title lang="en">Ranking DIRECTV Sports</title>
    <desc lang="en">Relato de jugadas, eventos más destacados y las noticias del día contadas desde un costado humorístico y desfachatado. Todos los bloopers, los mejores goles, las burradas, y mucho más.(n)</desc>
    <icon src="https://d5ip5p2ldkpmf.cloudfront.net/cinema/DB_Photos/ShowCards/AllMADPhotos/17402206/p17402206_b_v5_v1_cmd2.jpg" />
  </programme>
  <programme start="20220330053000 +0000" stop="20220330060000 +0000" channel="EC DIRECTV Sports 2">
    <title lang="en">NBA Action</title>
    <desc lang="en">Programa semanal con reportajes, entrevistas y toda la información de la liga de baloncesto más espectacular: la NBA. Incluye resúmenes de los partidos de la jornada y entrevistas a los personajes más destacados.(n)</desc>
  </programme>
  <programme start="20220330060000 +0000" stop="20220330070000 +0000" channel="EC DIRECTV Sports 2">
    <title lang="en">LaLiga SmartBank Highlights 2021-2022</title>
    <desc lang="en">Un repaso por los mejores goles y la acción más destacada de los campeonatos de la Segunda División y LaLiga de España.(n)</desc>
  </programme>
  <programme start="20220330070000 +0000" stop="20220330090000 +0000" channel="EC DIRECTV Sports 2">
    <title lang="en">Celta vs. Betis : Fútbol Español La Liga - Celta vs. Betis</title>
    <desc lang="en">Jornada 29 de LaLiga 2021-2022. Celta recibe a Betis en el estadio Balaídos. Los celtiñas solo ganaron 1 de sus últimos 5 partidos (2PE 2PP), mientras que los béticos vienen de ser eliminados en Europa League por el Eintracht Frankfurt.(n)</desc>
    <icon src="https://d5ip5p2ldkpmf.cloudfront.net/cinema/DB_Photos/ShowCards/AllMADPhotos/3609994/p3609994_b_v5_v9_cmd2.jpg" />
  </programme>
  <programme start="20220330090000 +0000" stop="20220330100000 +0000" channel="EC DIRECTV Sports 2">
    <title lang="en">Real Madrid TV</title>
    <desc lang="en">Información del equipo, entrevistas, reportajes, noticias y resúmenes de los partidos. Análisis y debate sobre todas las competiciones tanto de la sección de fútbol como de la de baloncesto.(n)</desc>
  </programme>
  <programme start="20220330100000 +0000" stop="20220330120000 +0000" channel="EC DIRECTV Sports 2">
    <title lang="en">Dinamarca vs. Serbia : Fútbol - Dinamarca vs. Serbia</title>
    <desc lang="en">Amistoso internacional. Dinamarca enfrenta a Serbia. Desde el Estadop Parken, en Copenhague, Dinamarca.(n)</desc>
  </programme>
  <programme start="20220330120000 +0000" stop="20220330123000 +0000" channel="EC DIRECTV Sports 2">
    <title lang="en">NBA Action</title>
    <desc lang="en">Programa semanal con reportajes, entrevistas y toda la información de la liga de baloncesto más espectacular: la NBA. Incluye resúmenes de los partidos de la jornada y entrevistas a los personajes más destacados.(n)</desc>
  </programme>
  <programme start="20220330123000 +0000" stop="20220330130000 +0000" channel="EC DIRECTV Sports 2">
    <title lang="en">FIBA Basketball</title>
    <desc lang="en">Lo mejor de la Federación Internacional de Baloncesto.(n)</desc>
  </programme>
  <programme start="20220330130000 +0000" stop="20220330150000 +0000" channel="EC DIRECTV Sports 2">
    <title lang="en">El chiringuito de jugones</title>
  </programme>
  <programme start="20220330150000 +0000" stop="20220330153000 +0000" channel="EC DIRECTV Sports 2">
    <title lang="en">UEFA European Qualifiers Highlights</title>
    <desc lang="en">Toda la acción con los mejores resúmenes y partidos de la clasificación europea.(n)</desc>
  </programme>
  <programme start="20220330153000 +0000" stop="20220330163000 +0000" channel="EC DIRECTV Sports 2">
    <title lang="en">UEFA FMs Matchnight Highlights</title>
    <desc lang="en">Un vistazo a los mejores momentos y lo más destacado de los partidos de la UEFA.(n)</desc>
  </programme>
  <programme start="20220330163000 +0000" stop="20220330183000 +0000" channel="EC DIRECTV Sports 2">
    <title lang="en">España vs. Islandia : Fútbol - España vs. Islandia</title>
    <desc lang="en">Amistoso internacional. España enfrenta a Islandia en el Estadio de Riazor.(n)</desc>
  </programme>
  <programme start="20220330183000 +0000" stop="20220330190000 +0000" channel="EC DIRECTV Sports 2">
    <title lang="en">Diario NBA</title>
    <desc lang="en">Una mirada en detalle con el resumen de los mejores momentos de la jornada. El jugador destacado, las mejores encestadas y las noticias del mejor baloncesto del planeta.(n)</desc>
  </programme>
  <programme start="20220330190000 +0000" stop="20220330220000 +0000" channel="EC DIRECTV Sports 2">
    <title lang="en">Barca TV - 2013-2014: Barcelona vs. Sevilla</title>
    <desc lang="en">Jornada 4. Partido disputado el 14 de septiembre de 2013.(n)</desc>
  </programme>
  <programme start="20220330220000 +0000" stop="20220330223000 +0000" channel="EC DIRECTV Sports 2">
    <title lang="en">Vamos a la Caye : Ezequiel Fernández Moores - Ezequiel Fernández Moores</title>
    <desc lang="en">El programa de entrevistas más descontracturado y particular, con los testimonios más originales. Las principales figuras del mundo del deporte repasan su carrera, relatan las mejores anécdotas y cuentan historias, hasta entonces, inéditas.(n)</desc>
  </programme>
  <programme start="20220330223000 +0000" stop="20220330230000 +0000" channel="EC DIRECTV Sports 2">
    <title lang="en">FIBA Basketball</title>
    <desc lang="en">Lo mejor de la Federación Internacional de Baloncesto.(n)</desc>
  </programme>
  <programme start="20220330230000 +0000" stop="20220330233000 +0000" channel="EC DIRECTV Sports 2">
    <title lang="en">DIRECTV Sports Gaming</title>
    <desc lang="en">Diego Korol junto a Kevo, Dalcru y Carolo. Te traen la mejor información, entrevistas y todas las novedades del mundo gamer.(n)</desc>
  </programme>
  <programme start="20220330233000 +0000" stop="20220331010000 +0000" channel="EC DIRECTV Sports 2">
    <title lang="en">Fútbol Total</title>
    <desc lang="en">Fútbol Total es el show futbolero más divertido de América Latina. El gran plantel de profesionales informa y analiza con un toque de humor las novedades de las ligas más relevantes del mundo.(n)</desc>
    <icon src="https://d5ip5p2ldkpmf.cloudfront.net/cinema/DB_Photos/ShowCards/AllMADPhotos/15284867/p15284867_b_v5_v1_cmd2.jpg" />
  </programme>
  <programme start="20220330010000 +0000" stop="20220330020000 +0000" channel="EC DIRECTV Sports Plus">
    <title lang="en">LaLiga SmartBank Highlights 2021-2022</title>
    <desc lang="en">Un repaso por los mejores goles y la acción más destacada de los campeonatos de la Segunda División y LaLiga de España.(n)</desc>
  </programme>
  <programme start="20220330020000 +0000" stop="20220330023000 +0000" channel="EC DIRECTV Sports Plus">
    <title lang="en">LaLiga Fans</title>
    <desc lang="en">Un programa dedicado a los aficionados muy especiales que siguen a los equipos que compiten en LaLiga.(n)</desc>
  </programme>
  <programme start="20220330023000 +0000" stop="20220330030000 +0000" channel="EC DIRECTV Sports Plus">
    <title lang="en">La Liga World</title>
    <desc lang="en">Magazine con entrevistas exclusivas con los mejores jugadores de la división y las antiguas leyendas de LaLiga.(n)</desc>
  </programme>
  <programme start="20220330030000 +0000" stop="20220330033000 +0000" channel="EC DIRECTV Sports Plus">
    <title lang="en">UEFA European Qualifiers Highlights</title>
    <desc lang="en">Toda la acción con los mejores resúmenes y partidos de la clasificación europea.(n)</desc>
  </programme>
  <programme start="20220330033000 +0000" stop="20220330043000 +0000" channel="EC DIRECTV Sports Plus">
    <title lang="en">UEFA FMs Matchnight Highlights</title>
    <desc lang="en">Un vistazo a los mejores momentos y lo más destacado de los partidos de la UEFA.(n)</desc>
  </programme>
  <programme start="20220330043000 +0000" stop="20220330063000 +0000" channel="EC DIRECTV Sports Plus">
    <title lang="en">Portugal vs. Macedonia : FIFA Eliminatorias Copa Mundial 2022 - Portugal vs. Macedonia</title>
    <desc lang="en">Final del repechaje por la clasificación. Portugal recibe a Macedonia del Norte en Oporto. Los lusos vienen de superar a Turquía por 3-1 y buscan su quinta participación mundialista. Los balcánicos, que nunca lo jugaron, vienen de eliminar a Italia.(n)</desc>
  </programme>
  <programme start="20220330063000 +0000" stop="20220330070000 +0000" channel="EC DIRECTV Sports Plus">
    <title lang="en">UEFA FMs Matchnight Highlights</title>
    <desc lang="en">Un vistazo a los mejores momentos y lo más destacado de los partidos de la UEFA.(n)</desc>
  </programme>
  <programme start="20220330070000 +0000" stop="20220330090000 +0000" channel="EC DIRECTV Sports Plus">
    <title lang="en">Alcorcón vs. Valladolid : Fútbol Español Segunda División - Alcorcón vs. Valladolid</title>
    <desc lang="en">Jornada 33 en la Segunda División. Alcorcón recibe a Valladolid en el estadio Santo Domingo. Los pucelanos, terceros con 58 puntos, intentarán enmendar las dos derrotas previas en su visita a Alcorcón, último con 18 puntos.(n)</desc>
  </programme>
  <programme start="20220330090000 +0000" stop="20220330110000 +0000" channel="EC DIRECTV Sports Plus">
    <title lang="en">Almería vs. Girona : Fútbol Español Segunda División - Almería vs. Girona</title>
    <desc lang="en">Jornada 33 en la Segunda División. Almería recibe a Girona en el Estadio de los Juegos Mediterráneos. Los catalanes, quintos con 52 puntos, visitan al segundo clasificado, un conjunto almeriense que suma 62 puntos.(n)</desc>
  </programme>
  <programme start="20220330110000 +0000" stop="20220330150000 +0000" channel="EC DIRECTV Sports Plus">
    <title lang="en">Real Madrid TV</title>
    <desc lang="en">Información del equipo, entrevistas, reportajes, noticias y resúmenes de los partidos. Análisis y debate sobre todas las competiciones tanto de la sección de fútbol como de la de baloncesto.(n)</desc>
  </programme>
  <programme start="20220330150000 +0000" stop="20220330170000 +0000" channel="EC DIRECTV Sports Plus">
    <title lang="en">Polonia vs. Suecia : FIFA Eliminatorias Copa Mundial 2022 - Polonia vs. Suecia</title>
    <desc lang="en">Final del repechaje por la clasificación. Polonia y Suecia se enfrentan en Stadion Slaski. Los locales llegan directamente a esta fase por la eliminación del equipo ruso. Los nórdicos, en tanto, superaron con angustia a República Checa (1-0).(n)</desc>
  </programme>
  <programme start="20220330170000 +0000" stop="20220330173000 +0000" channel="EC DIRECTV Sports Plus">
    <title lang="en">LaLiga Nations</title>
    <desc lang="en">La importancia y el valor de diferentes nacionalidades que han sido relevantes en la historia de LaLiga: Argentina, Reino Unido o Brasil son algunos ejemplos repasados en este programa.(n)</desc>
  </programme>
  <programme start="20220330173000 +0000" stop="20220330180000 +0000" channel="EC DIRECTV Sports Plus">
    <title lang="en">La Liga World</title>
    <desc lang="en">Magazine con entrevistas exclusivas con los mejores jugadores de la división y las antiguas leyendas de LaLiga.(n)</desc>
  </programme>
  <programme start="20220330180000 +0000" stop="20220330190000 +0000" channel="EC DIRECTV Sports Plus">
    <title lang="en">Conexión DIRECTV</title>
    <desc lang="en">El noticiero deportivo más completo de la región con la actualidad de cada disciplina y las novedades de las ligas más importantes del planeta. La información al instante y la palabra de los protagonistas en primera persona.(n)</desc>
  </programme>
  <programme start="20220330190000 +0000" stop="20220330210000 +0000" channel="EC DIRECTV Sports Plus">
    <title lang="en">Inglaterra vs. Costa de Marfil : Fútbol - Inglaterra vs. Costa de Marfil</title>
    <desc lang="en">Amistoso internacional. Inglaterra enfrenta a Costa de Marfil en el Estadio Wembley.(n)</desc>
  </programme>
  <programme start="20220330210000 +0000" stop="20220330220000 +0000" channel="EC DIRECTV Sports Plus">
    <title lang="en">Lo mejor de La Liga</title>
    <desc lang="en">Cobertura de La Liga de España, con comentarios, las mejores jugadas, goles, puntuaciones e información de los próximos partidos.(n)</desc>
  </programme>
  <programme start="20220330220000 +0000" stop="20220330230000 +0000" channel="EC DIRECTV Sports Plus">
    <title lang="en">LaLiga SmartBank Highlights 2021-2022</title>
    <desc lang="en">Un repaso por los mejores goles y la acción más destacada de los campeonatos de la Segunda División y LaLiga de España.(n)</desc>
  </programme>
  <programme start="20220330230000 +0000" stop="20220331010000 +0000" channel="EC DIRECTV Sports Plus">
    <title lang="en">Real Madrid vs. Barcelona : Fútbol Español La Liga - Real Madrid vs. Barcelona</title>
    <desc lang="en">Jornada 29 de LaLiga 2021-2022. Real Madrid recibe a Barcelona en el estadio Santiago Bernabéu. Los merengues acumulan 5 victorias seguidas y 6 juegos sin perder ante los culés. La última derrota fue en 2019 por 1-0 con gol de Ivan Rakitic.(n)</desc>
    <icon src="https://d5ip5p2ldkpmf.cloudfront.net/cinema/DB_Photos/ShowCards/AllMADPhotos/3609994/p3609994_b_v5_v9_cmd2.jpg" />
  </programme>
  <programme start="20220330160000 +0000" stop="20220330180000 +0000" channel="Win Sports +">
    <title lang="en">Millonarios vs. Junior (2021-II)</title>
    <icon src="https://ott-images.mediastre.am/winsports/assets/images/default.png" />
  </programme>
  <programme start="20220330180000 +0000" stop="20220330185000 +0000" channel="Win Sports +">
    <title lang="en">Win+ Noticias</title>
    <icon src="https://crop-platform-static.cdn.mdstrm.com/custom_files/526590f532b8fca13200005c/schedule/623e413bef42f20839c4b8c4/schedule-image/win-noticias-s.png" />
  </programme>
  <programme start="20220330185000 +0000" stop="20220330213000 +0000" channel="Win Sports +">
    <title lang="en">Copa BetPlay - Envigado vs. Bucaramanga</title>
    <icon src="https://ott-images.mediastre.am/winsports/assets/images/default.png" />
  </programme>
  <programme start="20220330213000 +0000" stop="20220330230000 +0000" channel="Win Sports +">
    <title lang="en">Saque Largo</title>
    <icon src="https://crop-platform-static.cdn.mdstrm.com/custom_files/526590f532b8fca13200005c/schedule/623e419a0c48bc084137622f/schedule-image/saque-largo-s.png" />
  </programme>
  <programme start="20220330230000 +0000" stop="20220331003000 +0000" channel="Win Sports +">
    <title lang="en">Conexión</title>
    <icon src="https://crop-platform-static.cdn.mdstrm.com/custom_files/526590f532b8fca13200005c/schedule/62446c469fbe6008365e5f1e/schedule-image/conexion-s.png" />
  </programme>
  <programme start="20220330143000 +0000" stop="20220330160500 +0000" channel="Showtime Familyzone West">
    <title lang="en">Love Means Zero</title>
  </programme>
  <programme start="20220330160500 +0000" stop="20220330173500 +0000" channel="Showtime Familyzone West">
    <title lang="en">Debunkers, Inc.</title>
  </programme>
  <programme start="20220330173500 +0000" stop="20220330190000 +0000" channel="Showtime Familyzone West">
    <title lang="en">The Fits</title>
  </programme>
  <programme start="20220330190000 +0000" stop="20220330204000 +0000" channel="Showtime Familyzone West">
    <title lang="en">Smokey and the Bandit</title>
  </programme>
  <programme start="20220330204000 +0000" stop="20220330220000 +0000" channel="Showtime Familyzone West">
    <title lang="en">Adam Sandler's Eight Crazy Nights</title>
  </programme>
  <programme start="20220330220000 +0000" stop="20220330234000 +0000" channel="Showtime Familyzone West">
    <title lang="en">The Challenger</title>
  </programme>
  <programme start="20220330234000 +0000" stop="20220331012000 +0000" channel="Showtime Familyzone West">
    <title lang="en">Rad</title>
  </programme>
  <programme start="20220330143200 +0000" stop="20220330162100 +0000" channel="Starz HD East (Dolby Available)">
    <title lang="en">Side Effects</title>
  </programme>
  <programme start="20220330162100 +0000" stop="20220330184400 +0000" channel="Starz HD East (Dolby Available)">
    <title lang="en">Eat Pray Love</title>
  </programme>
  <programme start="20220330184400 +0000" stop="20220330194200 +0000" channel="Starz HD East (Dolby Available)">
    <title lang="en">Power Book IV</title>
    <sub-title lang="en">He Ain't Heavy</sub-title>
  </programme>
  <programme start="20220330194200 +0000" stop="20220330214700 +0000" channel="Starz HD East (Dolby Available)">
    <title lang="en">Out Of Sight</title>
  </programme>
  <programme start="20220330214700 +0000" stop="20220330224500 +0000" channel="Starz HD East (Dolby Available)">
    <title lang="en">Power Book IV</title>
    <sub-title lang="en">He Ain't Heavy</sub-title>
  </programme>
  <programme start="20220330224500 +0000" stop="20220330234600 +0000" channel="Starz HD East (Dolby Available)">
    <title lang="en">Outlander</title>
    <sub-title lang="en">Hour of the Wolf</sub-title>
  </programme>
  <programme start="20220330234600 +0000" stop="20220331020000 +0000" channel="Starz HD East (Dolby Available)">
    <title lang="en">Marvel Studios' Iron Man 3</title>
  </programme>
  <programme start="20220330154900 +0000" stop="20220330172200 +0000" channel="Starz Edge HD East">
    <title lang="en">Approaching The Unknown</title>
  </programme>
  <programme start="20220330172200 +0000" stop="20220330175300 +0000" channel="Starz Edge HD East">
    <title lang="en">Shining Vale</title>
    <sub-title lang="en">The Squirrel Knew</sub-title>
  </programme>
  <programme start="20220330175300 +0000" stop="20220330193400 +0000" channel="Starz Edge HD East">
    <title lang="en">Don't Breathe 2</title>
  </programme>
  <programme start="20220330193400 +0000" stop="20220330210800 +0000" channel="Starz Edge HD East">
    <title lang="en">The Darjeeling Limited</title>
  </programme>
  <programme start="20220330210800 +0000" stop="20220330230800 +0000" channel="Starz Edge HD East">
    <title lang="en">Country Strong</title>
  </programme>
  <programme start="20220330230800 +0000" stop="20220331010000 +0000" channel="Starz Edge HD East">
    <title lang="en">Contraband</title>
  </programme>
  <programme start="20220330155900 +0000" stop="20220330174700 +0000" channel="Starz Kids &amp; Family HD East">
    <title lang="en">Little Boy</title>
  </programme>
  <programme start="20220330174700 +0000" stop="20220330192000 +0000" channel="Starz Kids &amp; Family HD East">
    <title lang="en">Babe</title>
  </programme>
  <programme start="20220330192000 +0000" stop="20220330204600 +0000" channel="Starz Kids &amp; Family HD East">
    <title lang="en">The Swan Princess Christmas</title>
  </programme>
  <programme start="20220330204600 +0000" stop="20220330222600 +0000" channel="Starz Kids &amp; Family HD East">
    <title lang="en">The Prize Winner of Defiance, Ohio</title>
  </programme>
  <programme start="20220330222600 +0000" stop="20220331000000 +0000" channel="Starz Kids &amp; Family HD East">
    <title lang="en">The Last Unicorn</title>
  </programme>
  <programme start="20220330155700 +0000" stop="20220330173400 +0000" channel="Starz inBlack HD East">
    <title lang="en">Kingdom Come</title>
  </programme>
  <programme start="20220330173400 +0000" stop="20220330200900 +0000" channel="Starz inBlack HD East">
    <title lang="en">Ray</title>
  </programme>
  <programme start="20220330200900 +0000" stop="20220330214800 +0000" channel="Starz inBlack HD East">
    <title lang="en">The House Next Door</title>
    <sub-title lang="en">Meet the Blacks 2</sub-title>
  </programme>
  <programme start="20220330214800 +0000" stop="20220330235700 +0000" channel="Starz inBlack HD East">
    <title lang="en">The Legend of Bagger Vance</title>
  </programme>
  <programme start="20220330235700 +0000" stop="20220331020000 +0000" channel="Starz inBlack HD East">
    <title lang="en">Equalizer 2</title>
  </programme>
  <programme start="20220330160000 +0000" stop="20220330173400 +0000" channel="Starz Cinema HD East">
    <title lang="en">The Last Shift</title>
  </programme>
  <programme start="20220330173400 +0000" stop="20220330192900 +0000" channel="Starz Cinema HD East">
    <title lang="en">Great Expectations</title>
  </programme>
  <programme start="20220330192900 +0000" stop="20220330203000 +0000" channel="Starz Cinema HD East">
    <title lang="en">Outlander</title>
    <sub-title lang="en">Hour of the Wolf</sub-title>
  </programme>
  <programme start="20220330203000 +0000" stop="20220330221200 +0000" channel="Starz Cinema HD East">
    <title lang="en">The Unholy</title>
  </programme>
  <programme start="20220330221200 +0000" stop="20220331001200 +0000" channel="Starz Cinema HD East">
    <title lang="en">Breathe</title>
  </programme>
  <programme start="20220330152100 +0000" stop="20220330170700 +0000" channel="Starz Comedy HD East">
    <title lang="en">28 Days</title>
  </programme>
  <programme start="20220330170700 +0000" stop="20220330190600 +0000" channel="Starz Comedy HD East">
    <title lang="en">Here Today</title>
  </programme>
  <programme start="20220330190600 +0000" stop="20220330204900 +0000" channel="Starz Comedy HD East">
    <title lang="en">National Lampoon's Vacation</title>
  </programme>
  <programme start="20220330204900 +0000" stop="20220330223300 +0000" channel="Starz Comedy HD East">
    <title lang="en">The Burbs</title>
  </programme>
  <programme start="20220330223300 +0000" stop="20220331000000 +0000" channel="Starz Comedy HD East">
    <title lang="en">Strange Wilderness</title>
  </programme>
  <programme start="20220330153000 +0000" stop="20220330174900 +0000" channel="Encore HD East">
    <title lang="en">John Grisham's The Rainmaker</title>
  </programme>
  <programme start="20220330174900 +0000" stop="20220330193000 +0000" channel="Encore HD East">
    <title lang="en">The Climb</title>
  </programme>
  <programme start="20220330193000 +0000" stop="20220330212200 +0000" channel="Encore HD East">
    <title lang="en">The Broken Hearts Gallery</title>
  </programme>
  <programme start="20220330212200 +0000" stop="20220330230000 +0000" channel="Encore HD East">
    <title lang="en">Yellow Rose</title>
  </programme>
  <programme start="20220330230000 +0000" stop="20220331010000 +0000" channel="Encore HD East">
    <title lang="en">U</title>
    <sub-title lang="en">571</sub-title>
  </programme>
  <programme start="20220330145400 +0000" stop="20220330162200 +0000" channel="Encore Action HD East">
    <title lang="en">Smokin' Aces 2</title>
    <sub-title lang="en">Assassins' Ball</sub-title>
  </programme>
  <programme start="20220330162200 +0000" stop="20220330175600 +0000" channel="Encore Action HD East">
    <title lang="en">The Marine 4</title>
    <sub-title lang="en">Moving Target</sub-title>
  </programme>
  <programme start="20220330175600 +0000" stop="20220330193500 +0000" channel="Encore Action HD East">
    <title lang="en">Tremors</title>
  </programme>
  <programme start="20220330193500 +0000" stop="20220330214500 +0000" channel="Encore Action HD East">
    <title lang="en">Maverick</title>
  </programme>
  <programme start="20220330214500 +0000" stop="20220331000000 +0000" channel="Encore Action HD East">
    <title lang="en">Legends of the Fall</title>
  </programme>
  <programme start="20220330160000 +0000" stop="20220330170000 +0000" channel="GOLPERU HD (GOLPERU HD)">
    <title lang="es">Código Fútbol</title>
    <desc lang="es">Un panel de expertos analiza y pone al debate los últimos acontecimientos de cada jornada y noticia del fútbol peruano e internacional.(n)</desc>
    <category lang="es">Reportaje</category>
    <category lang="es">Entrevista</category>
    <icon src="http://media.gvp.telefonica.com/storagearea0/IMAGES/00/09/73/9737026_2DC86F7D4EC0C346.jpg" />
    <country lang="es">PE</country>
    <rating system="MJColombia">
      <value>TE</value>
    </rating>
  </programme>
  <programme start="20220330170000 +0000" stop="20220330190000 +0000" channel="GOLPERU HD (GOLPERU HD)">
    <title lang="es">Gol Noticias</title>
    <desc lang="es">Noticiero con los acontecimientos más importantes del fútbol nacional e internacional, con entrevistas e imágenes exclusivas sobre la actualidad del balompié mundial.(n)</desc>
    <category lang="es">Reportaje</category>
    <category lang="es">Entrevista</category>
    <icon src="http://media.gvp.telefonica.com/storagearea0/IMAGES/00/09/73/9737219_94F28BA6CEEA261E.jpg" />
    <country lang="es">PE</country>
    <rating system="MJColombia">
      <value>TE</value>
    </rating>
  </programme>
  <programme start="20220330190000 +0000" stop="20220330210000 +0000" channel="GOLPERU HD (GOLPERU HD)">
    <title lang="es">Liga1</title>
    <sub-title lang="es">AD Cantolao vs. Universitario - Apertura, Fecha 1 (06-02-2022)</sub-title>
    <desc lang="es">AD Cantolao va por un triunfo en calidad de local que le permita obtener la ventaja desde la primera fecha del torneo, pero Universitario busca tres puntos de visita para iniciar la temporada con una victoria.(n)</desc>
    <category lang="es">Fútbol</category>
    <icon src="http://media.gvp.telefonica.com/storagearea0/IMAGES/00/10/70/10703076_FFEB233208FF3F8E.jpg" />
    <country lang="es">PE</country>
    <episode-num system="onscreen">S2022</episode-num>
    <rating system="MJColombia">
      <value>TE</value>
    </rating>
  </programme>
  <programme start="20220330210000 +0000" stop="20220330213000 +0000" channel="GOLPERU HD (GOLPERU HD)">
    <title lang="es">Charlas de cuarentena</title>
    <sub-title lang="es">Claudio Pizarro</sub-title>
    <desc lang="es">Disfruta de las mejores conversaciones de fútbol, recuerda los momentos que marcaron la historia y conoce las anécdotas ocurridas en la carrera del exfutbolista peruano, Claudio Pizarro.(n)</desc>
    <category lang="es">Entrevista</category>
    <category lang="es">Fútbol</category>
    <icon src="http://media.gvp.telefonica.com/storagearea0/IMAGES/00/09/73/9737024_ED99A65259F2624C.jpg" />
    <country lang="es">PE</country>
    <episode-num system="onscreen">S2020</episode-num>
    <rating system="MJColombia">
      <value>TE</value>
    </rating>
  </programme>
  <programme start="20220330213000 +0000" stop="20220330220000 +0000" channel="GOLPERU HD (GOLPERU HD)">
    <title lang="es">Once Ideal</title>
    <desc lang="es">Programa que analiza las estadísticas de los rendimientos de los jugadores para debatir y armar el mejor equipo de la fecha de la Liga1.(n)</desc>
    <category lang="es">Fútbol</category>
    <category lang="es">Deportes</category>
    <icon src="http://media.gvp.telefonica.com/storagearea0/IMAGES/00/09/74/9741107_E4D75746C60977A2.jpg" />
    <country lang="es">PE</country>
    <rating system="MJColombia">
      <value>TE</value>
    </rating>
  </programme>
  <programme start="20220330220000 +0000" stop="20220330223000 +0000" channel="GOLPERU HD (GOLPERU HD)">
    <title lang="es">10 x 10</title>
    <desc lang="es">Programa en donde se presentan las diez noticias más destacadas e importantes que se desarrollan durante el día dentro del mundo futbolístico tanto a nivel nacional como internacional, contadas y analizadas con el estilo único y propio de los conductores.(n)</desc>
    <category lang="es">Fútbol</category>
    <category lang="es">Noticias</category>
    <icon src="http://media.gvp.telefonica.com/storagearea0/IMAGES/00/09/74/9741084_8F03ED82D25301AF.jpg" />
    <country lang="es">PE</country>
    <rating system="MJColombia">
      <value>TE</value>
    </rating>
  </programme>
</tv>